{
        "servers": [
        {
            "server_id": "1",
            "hostname": "United States",
            "flag": "united_states_of_america",
            "ip": "209.145.50.85",
            "status": "1",
            "type": "1",
            "Priority": "1",
            "operators": "ir-mci"
        },
        {
            "server_id": "47",
            "hostname": "United States",
            "flag": "united_states_of_america",
            "ip": "74.208.139.23",
            "status": "1",
            "type": "1",
            "Priority": "1",
            "operators": "irancell,mtn-irancell,mtnirancell"
        }
    ],
    "config": {
        "type": "2",
        "App_Id": "ca-app-pub-5033755012244285~4064993933",
        "acunit": "ca-app-pub-5033755012244285/6269034187",
        "bcunit": "ca-app-pub-5033755012244285/4911775355",
        "native": "ca-app-pub-5033755012244285/3598638815",
        "splash": "ca-app-pub-5033755012244285/7812667255",
        "dcunit": "ca-app-pub-5033755012244285/1164047161",
        "rewarded": "ca-app-pub-5033755012244285/2530267981",
        "versioncode": "6",
        "buttontext": "Update",
        "updatetext": "New version available. Update to get new features.",
        "isforceupdate": 0,
        "downloadlink": "https://www.dropbox.com/s/3i7neb6a9wzbx1f/centos-docker.txt?dl=1"
    }
}
