{"servers":[{"server_id":"9-1","hostname":"United States","flag":"united_states","hostname_fa":"United States","ip":"lmn1709465405522.lmn15388.info","status":1,"type":"0","Priority":"1","clients":8156,"port":443,"redirectTo":"lmn1009.sbs","config":"{\"log\":{\"access\":\"\",\"error\":\"\",\"loglevel\":\"warning\"},\"inbounds\":[{\"tag\":\"socks\",\"port\":10808,\"listen\":\"127.0.0.1\",\"protocol\":\"socks\",\"sniffing\":{\"enabled\":true,\"destOverride\":[\"http\",\"tls\"],\"routeOnly\":false},\"settings\":{\"auth\":\"noauth\",\"udp\":true,\"allowTransparent\":false}},{\"tag\":\"http\",\"port\":10809,\"listen\":\"127.0.0.1\",\"protocol\":\"http\",\"sniffing\":{\"enabled\":true,\"destOverride\":[\"http\",\"tls\"],\"routeOnly\":false},\"settings\":{\"auth\":\"noauth\",\"udp\":true,\"allowTransparent\":false}}],\"outbounds\":[{\"tag\":\"proxy\",\"protocol\":\"vless\",\"settings\":{\"vnext\":[{\"address\":\"104.31.16.66\",\"port\":443,\"users\":[{\"id\":\"376b9861-2fc6-4647-959c-18185cd9c95a\",\"alterId\":0,\"email\":\"t@t.tt\",\"security\":\"auto\",\"encryption\":\"none\",\"flow\":\"\"}]}]},\"streamSettings\":{\"network\":\"ws\",\"security\":\"tls\",\"tlsSettings\":{\"allowInsecure\":true,\"serverName\":\"lmn1709465405522.lmn15388.info\",\"alpn\":[\"h2\",\"http/1.1\"],\"fingerprint\":\"chrome\",\"show\":false},\"wsSettings\":{\"path\":\"/hz-9ws\",\"headers\":{\"Host\":\"lmn1709465405522.lmn15388.info\"}},\"sockopt\":{\"dialerProxy\":\"fragment\",\"tcpKeepAliveIdle\":100,\"mark\":255}},\"mux\":{\"enabled\":false,\"concurrency\":-1}},{\"tag\":\"fragment\",\"protocol\":\"freedom\",\"settings\":{\"fragment\":{\"packets\":\"tlshello\",\"length\":\"10-20\",\"interval\":\"10-20\"}},\"streamSettings\":{\"sockopt\":{\"TcpNoDelay\":true,\"tcpKeepAliveIdle\":100,\"mark\":255}}},{\"tag\":\"direct\",\"protocol\":\"freedom\",\"settings\":{}},{\"tag\":\"block\",\"protocol\":\"blackhole\",\"settings\":{\"response\":{\"type\":\"http\"}}}],\"routing\":{\"domainStrategy\":\"AsIs\",\"rules\":[{\"type\":\"field\",\"inboundTag\":[\"api\"],\"outboundTag\":\"api\",\"enabled\":true},{\"id\":\"5465425548310166497\",\"type\":\"field\",\"outboundTag\":\"direct\",\"domain\":[\"domain:ir\",\"geosite:cn\"],\"enabled\":true},{\"id\":\"5425034033205580637\",\"type\":\"field\",\"outboundTag\":\"direct\",\"ip\":[\"geoip:private\",\"geoip:cn\",\"geoip:ir\"],\"enabled\":true},{\"id\":\"5627785659655799759\",\"type\":\"field\",\"port\":\"0-65535\",\"outboundTag\":\"proxy\",\"enabled\":true}]}}"},{"server_id":"20-1","hostname":"United States","flag":"united_states","hostname_fa":"United States","ip":"lmn1709465405713.lmn15396.info","status":1,"type":"0","Priority":"1","clients":{},"port":443,"redirectTo":"lmn1020.sbs","config":"{\"log\":{\"access\":\"\",\"error\":\"\",\"loglevel\":\"warning\"},\"inbounds\":[{\"tag\":\"socks\",\"port\":10808,\"listen\":\"127.0.0.1\",\"protocol\":\"socks\",\"sniffing\":{\"enabled\":true,\"destOverride\":[\"http\",\"tls\"],\"routeOnly\":false},\"settings\":{\"auth\":\"noauth\",\"udp\":true,\"allowTransparent\":false}},{\"tag\":\"http\",\"port\":10809,\"listen\":\"127.0.0.1\",\"protocol\":\"http\",\"sniffing\":{\"enabled\":true,\"destOverride\":[\"http\",\"tls\"],\"routeOnly\":false},\"settings\":{\"auth\":\"noauth\",\"udp\":true,\"allowTransparent\":false}}],\"outbounds\":[{\"tag\":\"proxy\",\"protocol\":\"vless\",\"settings\":{\"vnext\":[{\"address\":\"104.31.16.66\",\"port\":443,\"users\":[{\"id\":\"376b9861-2fc6-4647-959c-18185cd9c95a\",\"alterId\":0,\"email\":\"t@t.tt\",\"security\":\"auto\",\"encryption\":\"none\",\"flow\":\"\"}]}]},\"streamSettings\":{\"network\":\"ws\",\"security\":\"tls\",\"tlsSettings\":{\"allowInsecure\":true,\"serverName\":\"lmn1709465405713.lmn15396.info\",\"alpn\":[\"h2\",\"http/1.1\"],\"fingerprint\":\"chrome\",\"show\":false},\"wsSettings\":{\"path\":\"/hz2-7ws\",\"headers\":{\"Host\":\"lmn1709465405713.lmn15396.info\"}},\"sockopt\":{\"dialerProxy\":\"fragment\",\"tcpKeepAliveIdle\":100,\"mark\":255}},\"mux\":{\"enabled\":false,\"concurrency\":-1}},{\"tag\":\"fragment\",\"protocol\":\"freedom\",\"settings\":{\"fragment\":{\"packets\":\"tlshello\",\"length\":\"10-20\",\"interval\":\"10-20\"}},\"streamSettings\":{\"sockopt\":{\"TcpNoDelay\":true,\"tcpKeepAliveIdle\":100,\"mark\":255}}},{\"tag\":\"direct\",\"protocol\":\"freedom\",\"settings\":{}},{\"tag\":\"block\",\"protocol\":\"blackhole\",\"settings\":{\"response\":{\"type\":\"http\"}}}],\"routing\":{\"domainStrategy\":\"AsIs\",\"rules\":[{\"type\":\"field\",\"inboundTag\":[\"api\"],\"outboundTag\":\"api\",\"enabled\":true},{\"id\":\"5465425548310166497\",\"type\":\"field\",\"outboundTag\":\"direct\",\"domain\":[\"domain:ir\",\"geosite:cn\"],\"enabled\":true},{\"id\":\"5425034033205580637\",\"type\":\"field\",\"outboundTag\":\"direct\",\"ip\":[\"geoip:private\",\"geoip:cn\",\"geoip:ir\"],\"enabled\":true},{\"id\":\"5627785659655799759\",\"type\":\"field\",\"port\":\"0-65535\",\"outboundTag\":\"proxy\",\"enabled\":true}]}}"},{"server_id":"10-1","hostname":"United States","flag":"united_states","hostname_fa":"United States","ip":"lmn1709465405535.lmn15366.info","status":1,"type":"1","Priority":"1","clients":{},"port":443,"redirectTo":"lmn1010.sbs","config":"{\"log\":{\"access\":\"\",\"error\":\"\",\"loglevel\":\"warning\"},\"inbounds\":[{\"tag\":\"socks\",\"port\":10808,\"listen\":\"127.0.0.1\",\"protocol\":\"socks\",\"sniffing\":{\"enabled\":true,\"destOverride\":[\"http\",\"tls\"],\"routeOnly\":false},\"settings\":{\"auth\":\"noauth\",\"udp\":true,\"allowTransparent\":false}},{\"tag\":\"http\",\"port\":10809,\"listen\":\"127.0.0.1\",\"protocol\":\"http\",\"sniffing\":{\"enabled\":true,\"destOverride\":[\"http\",\"tls\"],\"routeOnly\":false},\"settings\":{\"auth\":\"noauth\",\"udp\":true,\"allowTransparent\":false}}],\"outbounds\":[{\"tag\":\"proxy\",\"protocol\":\"vless\",\"settings\":{\"vnext\":[{\"address\":\"104.31.16.66\",\"port\":443,\"users\":[{\"id\":\"376b9861-2fc6-4647-959c-18185cd9c95a\",\"alterId\":0,\"email\":\"t@t.tt\",\"security\":\"auto\",\"encryption\":\"none\",\"flow\":\"\"}]}]},\"streamSettings\":{\"network\":\"ws\",\"security\":\"tls\",\"tlsSettings\":{\"allowInsecure\":true,\"serverName\":\"lmn1709465405535.lmn15366.info\",\"alpn\":[\"h2\",\"http/1.1\"],\"fingerprint\":\"chrome\",\"show\":false},\"wsSettings\":{\"path\":\"/hz-10ws\",\"headers\":{\"Host\":\"lmn1709465405535.lmn15366.info\"}},\"sockopt\":{\"dialerProxy\":\"fragment\",\"tcpKeepAliveIdle\":100,\"mark\":255}},\"mux\":{\"enabled\":false,\"concurrency\":-1}},{\"tag\":\"fragment\",\"protocol\":\"freedom\",\"settings\":{\"fragment\":{\"packets\":\"tlshello\",\"length\":\"10-20\",\"interval\":\"10-20\"}},\"streamSettings\":{\"sockopt\":{\"TcpNoDelay\":true,\"tcpKeepAliveIdle\":100,\"mark\":255}}},{\"tag\":\"direct\",\"protocol\":\"freedom\",\"settings\":{}},{\"tag\":\"block\",\"protocol\":\"blackhole\",\"settings\":{\"response\":{\"type\":\"http\"}}}],\"routing\":{\"domainStrategy\":\"AsIs\",\"rules\":[{\"type\":\"field\",\"inboundTag\":[\"api\"],\"outboundTag\":\"api\",\"enabled\":true},{\"id\":\"5465425548310166497\",\"type\":\"field\",\"outboundTag\":\"direct\",\"domain\":[\"domain:ir\",\"geosite:cn\"],\"enabled\":true},{\"id\":\"5425034033205580637\",\"type\":\"field\",\"outboundTag\":\"direct\",\"ip\":[\"geoip:private\",\"geoip:cn\",\"geoip:ir\"],\"enabled\":true},{\"id\":\"5627785659655799759\",\"type\":\"field\",\"port\":\"0-65535\",\"outboundTag\":\"proxy\",\"enabled\":true}]}}"},{"server_id":"18-1","hostname":"Spain","flag":"spain","hostname_fa":"Spain","ip":"lmn1709465405552.lmn15376.info","status":1,"type":"0","Priority":"1","clients":{},"port":443,"redirectTo":"lmn1038.sbs","config":"{\"log\":{\"access\":\"\",\"error\":\"\",\"loglevel\":\"warning\"},\"inbounds\":[{\"tag\":\"socks\",\"port\":10808,\"listen\":\"127.0.0.1\",\"protocol\":\"socks\",\"sniffing\":{\"enabled\":true,\"destOverride\":[\"http\",\"tls\"],\"routeOnly\":false},\"settings\":{\"auth\":\"noauth\",\"udp\":true,\"allowTransparent\":false}},{\"tag\":\"http\",\"port\":10809,\"listen\":\"127.0.0.1\",\"protocol\":\"http\",\"sniffing\":{\"enabled\":true,\"destOverride\":[\"http\",\"tls\"],\"routeOnly\":false},\"settings\":{\"auth\":\"noauth\",\"udp\":true,\"allowTransparent\":false}}],\"outbounds\":[{\"tag\":\"proxy\",\"protocol\":\"vless\",\"settings\":{\"vnext\":[{\"address\":\"104.31.16.66\",\"port\":443,\"users\":[{\"id\":\"376b9861-2fc6-4647-959c-18185cd9c95a\",\"alterId\":0,\"email\":\"t@t.tt\",\"security\":\"auto\",\"encryption\":\"none\",\"flow\":\"\"}]}]},\"streamSettings\":{\"network\":\"ws\",\"security\":\"tls\",\"tlsSettings\":{\"allowInsecure\":true,\"serverName\":\"lmn1709465405552.lmn15376.info\",\"alpn\":[\"h2\",\"http/1.1\"],\"fingerprint\":\"chrome\",\"show\":false},\"wsSettings\":{\"path\":\"/hz2-3ws\",\"headers\":{\"Host\":\"lmn1709465405552.lmn15376.info\"}},\"sockopt\":{\"dialerProxy\":\"fragment\",\"tcpKeepAliveIdle\":100,\"mark\":255}},\"mux\":{\"enabled\":false,\"concurrency\":-1}},{\"tag\":\"fragment\",\"protocol\":\"freedom\",\"settings\":{\"fragment\":{\"packets\":\"tlshello\",\"length\":\"10-20\",\"interval\":\"10-20\"}},\"streamSettings\":{\"sockopt\":{\"TcpNoDelay\":true,\"tcpKeepAliveIdle\":100,\"mark\":255}}},{\"tag\":\"direct\",\"protocol\":\"freedom\",\"settings\":{}},{\"tag\":\"block\",\"protocol\":\"blackhole\",\"settings\":{\"response\":{\"type\":\"http\"}}}],\"routing\":{\"domainStrategy\":\"AsIs\",\"rules\":[{\"type\":\"field\",\"inboundTag\":[\"api\"],\"outboundTag\":\"api\",\"enabled\":true},{\"id\":\"5465425548310166497\",\"type\":\"field\",\"outboundTag\":\"direct\",\"domain\":[\"domain:ir\",\"geosite:cn\"],\"enabled\":true},{\"id\":\"5425034033205580637\",\"type\":\"field\",\"outboundTag\":\"direct\",\"ip\":[\"geoip:private\",\"geoip:cn\",\"geoip:ir\"],\"enabled\":true},{\"id\":\"5627785659655799759\",\"type\":\"field\",\"port\":\"0-65535\",\"outboundTag\":\"proxy\",\"enabled\":true}]}}"},{"server_id":"15-1","hostname":"Finland","flag":"finland","hostname_fa":"Finland","ip":"lmn1709465405542.lmn15380.info","status":1,"type":"0","Priority":"1","clients":{},"port":443,"redirectTo":"lmn1015.sbs","config":"{\"log\":{\"access\":\"\",\"error\":\"\",\"loglevel\":\"warning\"},\"inbounds\":[{\"tag\":\"socks\",\"port\":10808,\"listen\":\"127.0.0.1\",\"protocol\":\"socks\",\"sniffing\":{\"enabled\":true,\"destOverride\":[\"http\",\"tls\"],\"routeOnly\":false},\"settings\":{\"auth\":\"noauth\",\"udp\":true,\"allowTransparent\":false}},{\"tag\":\"http\",\"port\":10809,\"listen\":\"127.0.0.1\",\"protocol\":\"http\",\"sniffing\":{\"enabled\":true,\"destOverride\":[\"http\",\"tls\"],\"routeOnly\":false},\"settings\":{\"auth\":\"noauth\",\"udp\":true,\"allowTransparent\":false}}],\"outbounds\":[{\"tag\":\"proxy\",\"protocol\":\"vless\",\"settings\":{\"vnext\":[{\"address\":\"104.31.16.66\",\"port\":443,\"users\":[{\"id\":\"376b9861-2fc6-4647-959c-18185cd9c95a\",\"alterId\":0,\"email\":\"t@t.tt\",\"security\":\"auto\",\"encryption\":\"none\",\"flow\":\"\"}]}]},\"streamSettings\":{\"network\":\"ws\",\"security\":\"tls\",\"tlsSettings\":{\"allowInsecure\":true,\"serverName\":\"lmn1709465405542.lmn15380.info\",\"alpn\":[\"h2\",\"http/1.1\"],\"fingerprint\":\"chrome\",\"show\":false},\"wsSettings\":{\"path\":\"/hz3-1ws\",\"headers\":{\"Host\":\"lmn1709465405542.lmn15380.info\"}},\"sockopt\":{\"dialerProxy\":\"fragment\",\"tcpKeepAliveIdle\":100,\"mark\":255}},\"mux\":{\"enabled\":false,\"concurrency\":-1}},{\"tag\":\"fragment\",\"protocol\":\"freedom\",\"settings\":{\"fragment\":{\"packets\":\"tlshello\",\"length\":\"10-20\",\"interval\":\"10-20\"}},\"streamSettings\":{\"sockopt\":{\"TcpNoDelay\":true,\"tcpKeepAliveIdle\":100,\"mark\":255}}},{\"tag\":\"direct\",\"protocol\":\"freedom\",\"settings\":{}},{\"tag\":\"block\",\"protocol\":\"blackhole\",\"settings\":{\"response\":{\"type\":\"http\"}}}],\"routing\":{\"domainStrategy\":\"AsIs\",\"rules\":[{\"type\":\"field\",\"inboundTag\":[\"api\"],\"outboundTag\":\"api\",\"enabled\":true},{\"id\":\"5465425548310166497\",\"type\":\"field\",\"outboundTag\":\"direct\",\"domain\":[\"domain:ir\",\"geosite:cn\"],\"enabled\":true},{\"id\":\"5425034033205580637\",\"type\":\"field\",\"outboundTag\":\"direct\",\"ip\":[\"geoip:private\",\"geoip:cn\",\"geoip:ir\"],\"enabled\":true},{\"id\":\"5627785659655799759\",\"type\":\"field\",\"port\":\"0-65535\",\"outboundTag\":\"proxy\",\"enabled\":true}]}}"},{"server_id":"4-1","hostname":"United Kingdom","flag":"united_kingdom","hostname_fa":"United Kingdom","ip":"lmn1709465405540.lmn15384.info","status":1,"type":"1","Priority":"1","clients":{},"port":443,"redirectTo":"lmn1004.sbs","config":"{\"log\":{\"access\":\"\",\"error\":\"\",\"loglevel\":\"warning\"},\"inbounds\":[{\"tag\":\"socks\",\"port\":10808,\"listen\":\"127.0.0.1\",\"protocol\":\"socks\",\"sniffing\":{\"enabled\":true,\"destOverride\":[\"http\",\"tls\"],\"routeOnly\":false},\"settings\":{\"auth\":\"noauth\",\"udp\":true,\"allowTransparent\":false}},{\"tag\":\"http\",\"port\":10809,\"listen\":\"127.0.0.1\",\"protocol\":\"http\",\"sniffing\":{\"enabled\":true,\"destOverride\":[\"http\",\"tls\"],\"routeOnly\":false},\"settings\":{\"auth\":\"noauth\",\"udp\":true,\"allowTransparent\":false}}],\"outbounds\":[{\"tag\":\"proxy\",\"protocol\":\"vless\",\"settings\":{\"vnext\":[{\"address\":\"104.31.16.66\",\"port\":443,\"users\":[{\"id\":\"376b9861-2fc6-4647-959c-18185cd9c95a\",\"alterId\":0,\"email\":\"t@t.tt\",\"security\":\"auto\",\"encryption\":\"none\",\"flow\":\"\"}]}]},\"streamSettings\":{\"network\":\"ws\",\"security\":\"tls\",\"tlsSettings\":{\"allowInsecure\":true,\"serverName\":\"lmn1709465405540.lmn15384.info\",\"alpn\":[\"h2\",\"http/1.1\"],\"fingerprint\":\"chrome\",\"show\":false},\"wsSettings\":{\"path\":\"/hz-4ws\",\"headers\":{\"Host\":\"lmn1709465405540.lmn15384.info\"}},\"sockopt\":{\"dialerProxy\":\"fragment\",\"tcpKeepAliveIdle\":100,\"mark\":255}},\"mux\":{\"enabled\":false,\"concurrency\":-1}},{\"tag\":\"fragment\",\"protocol\":\"freedom\",\"settings\":{\"fragment\":{\"packets\":\"tlshello\",\"length\":\"10-20\",\"interval\":\"10-20\"}},\"streamSettings\":{\"sockopt\":{\"TcpNoDelay\":true,\"tcpKeepAliveIdle\":100,\"mark\":255}}},{\"tag\":\"direct\",\"protocol\":\"freedom\",\"settings\":{}},{\"tag\":\"block\",\"protocol\":\"blackhole\",\"settings\":{\"response\":{\"type\":\"http\"}}}],\"routing\":{\"domainStrategy\":\"AsIs\",\"rules\":[{\"type\":\"field\",\"inboundTag\":[\"api\"],\"outboundTag\":\"api\",\"enabled\":true},{\"id\":\"5465425548310166497\",\"type\":\"field\",\"outboundTag\":\"direct\",\"domain\":[\"domain:ir\",\"geosite:cn\"],\"enabled\":true},{\"id\":\"5425034033205580637\",\"type\":\"field\",\"outboundTag\":\"direct\",\"ip\":[\"geoip:private\",\"geoip:cn\",\"geoip:ir\"],\"enabled\":true},{\"id\":\"5627785659655799759\",\"type\":\"field\",\"port\":\"0-65535\",\"outboundTag\":\"proxy\",\"enabled\":true}]}}"},{"server_id":"22-1","hostname":"United States","flag":"united_states","hostname_fa":"United States","ip":"lmn1709465405625.lmn15380.info","status":1,"type":"0","Priority":"1","clients":{},"port":443,"redirectTo":"lmn1022.sbs","config":"{\"log\":{\"access\":\"\",\"error\":\"\",\"loglevel\":\"warning\"},\"inbounds\":[{\"tag\":\"socks\",\"port\":10808,\"listen\":\"127.0.0.1\",\"protocol\":\"socks\",\"sniffing\":{\"enabled\":true,\"destOverride\":[\"http\",\"tls\"],\"routeOnly\":false},\"settings\":{\"auth\":\"noauth\",\"udp\":true,\"allowTransparent\":false}},{\"tag\":\"http\",\"port\":10809,\"listen\":\"127.0.0.1\",\"protocol\":\"http\",\"sniffing\":{\"enabled\":true,\"destOverride\":[\"http\",\"tls\"],\"routeOnly\":false},\"settings\":{\"auth\":\"noauth\",\"udp\":true,\"allowTransparent\":false}}],\"outbounds\":[{\"tag\":\"proxy\",\"protocol\":\"vless\",\"settings\":{\"vnext\":[{\"address\":\"104.31.16.66\",\"port\":443,\"users\":[{\"id\":\"376b9861-2fc6-4647-959c-18185cd9c95a\",\"alterId\":0,\"email\":\"t@t.tt\",\"security\":\"auto\",\"encryption\":\"none\",\"flow\":\"\"}]}]},\"streamSettings\":{\"network\":\"ws\",\"security\":\"tls\",\"tlsSettings\":{\"allowInsecure\":true,\"serverName\":\"lmn1709465405625.lmn15380.info\",\"alpn\":[\"h2\",\"http/1.1\"],\"fingerprint\":\"chrome\",\"show\":false},\"wsSettings\":{\"path\":\"/hz3-3ws\",\"headers\":{\"Host\":\"lmn1709465405625.lmn15380.info\"}},\"sockopt\":{\"dialerProxy\":\"fragment\",\"tcpKeepAliveIdle\":100,\"mark\":255}},\"mux\":{\"enabled\":false,\"concurrency\":-1}},{\"tag\":\"fragment\",\"protocol\":\"freedom\",\"settings\":{\"fragment\":{\"packets\":\"tlshello\",\"length\":\"10-20\",\"interval\":\"10-20\"}},\"streamSettings\":{\"sockopt\":{\"TcpNoDelay\":true,\"tcpKeepAliveIdle\":100,\"mark\":255}}},{\"tag\":\"direct\",\"protocol\":\"freedom\",\"settings\":{}},{\"tag\":\"block\",\"protocol\":\"blackhole\",\"settings\":{\"response\":{\"type\":\"http\"}}}],\"routing\":{\"domainStrategy\":\"AsIs\",\"rules\":[{\"type\":\"field\",\"inboundTag\":[\"api\"],\"outboundTag\":\"api\",\"enabled\":true},{\"id\":\"5465425548310166497\",\"type\":\"field\",\"outboundTag\":\"direct\",\"domain\":[\"domain:ir\",\"geosite:cn\"],\"enabled\":true},{\"id\":\"5425034033205580637\",\"type\":\"field\",\"outboundTag\":\"direct\",\"ip\":[\"geoip:private\",\"geoip:cn\",\"geoip:ir\"],\"enabled\":true},{\"id\":\"5627785659655799759\",\"type\":\"field\",\"port\":\"0-65535\",\"outboundTag\":\"proxy\",\"enabled\":true}]}}"},{"server_id":"8-1","hostname":"United States","flag":"united_states","hostname_fa":"United States","ip":"lmn1709465405530.lmn15372.info","status":1,"type":"0","Priority":"1","clients":{},"port":443,"redirectTo":"lmn1008.sbs","config":"{\"log\":{\"access\":\"\",\"error\":\"\",\"loglevel\":\"warning\"},\"inbounds\":[{\"tag\":\"socks\",\"port\":10808,\"listen\":\"127.0.0.1\",\"protocol\":\"socks\",\"sniffing\":{\"enabled\":true,\"destOverride\":[\"http\",\"tls\"],\"routeOnly\":false},\"settings\":{\"auth\":\"noauth\",\"udp\":true,\"allowTransparent\":false}},{\"tag\":\"http\",\"port\":10809,\"listen\":\"127.0.0.1\",\"protocol\":\"http\",\"sniffing\":{\"enabled\":true,\"destOverride\":[\"http\",\"tls\"],\"routeOnly\":false},\"settings\":{\"auth\":\"noauth\",\"udp\":true,\"allowTransparent\":false}}],\"outbounds\":[{\"tag\":\"proxy\",\"protocol\":\"vless\",\"settings\":{\"vnext\":[{\"address\":\"104.31.16.66\",\"port\":443,\"users\":[{\"id\":\"376b9861-2fc6-4647-959c-18185cd9c95a\",\"alterId\":0,\"email\":\"t@t.tt\",\"security\":\"auto\",\"encryption\":\"none\",\"flow\":\"\"}]}]},\"streamSettings\":{\"network\":\"ws\",\"security\":\"tls\",\"tlsSettings\":{\"allowInsecure\":true,\"serverName\":\"lmn1709465405530.lmn15372.info\",\"alpn\":[\"h2\",\"http/1.1\"],\"fingerprint\":\"chrome\",\"show\":false},\"wsSettings\":{\"path\":\"/hz-8ws\",\"headers\":{\"Host\":\"lmn1709465405530.lmn15372.info\"}},\"sockopt\":{\"dialerProxy\":\"fragment\",\"tcpKeepAliveIdle\":100,\"mark\":255}},\"mux\":{\"enabled\":false,\"concurrency\":-1}},{\"tag\":\"fragment\",\"protocol\":\"freedom\",\"settings\":{\"fragment\":{\"packets\":\"tlshello\",\"length\":\"10-20\",\"interval\":\"10-20\"}},\"streamSettings\":{\"sockopt\":{\"TcpNoDelay\":true,\"tcpKeepAliveIdle\":100,\"mark\":255}}},{\"tag\":\"direct\",\"protocol\":\"freedom\",\"settings\":{}},{\"tag\":\"block\",\"protocol\":\"blackhole\",\"settings\":{\"response\":{\"type\":\"http\"}}}],\"routing\":{\"domainStrategy\":\"AsIs\",\"rules\":[{\"type\":\"field\",\"inboundTag\":[\"api\"],\"outboundTag\":\"api\",\"enabled\":true},{\"id\":\"5465425548310166497\",\"type\":\"field\",\"outboundTag\":\"direct\",\"domain\":[\"domain:ir\",\"geosite:cn\"],\"enabled\":true},{\"id\":\"5425034033205580637\",\"type\":\"field\",\"outboundTag\":\"direct\",\"ip\":[\"geoip:private\",\"geoip:cn\",\"geoip:ir\"],\"enabled\":true},{\"id\":\"5627785659655799759\",\"type\":\"field\",\"port\":\"0-65535\",\"outboundTag\":\"proxy\",\"enabled\":true}]}}"},{"server_id":"28-1","hostname":"United States","flag":"united_states","hostname_fa":"United States","ip":"lmn1709465410589.lmn15393.info","status":1,"type":"1","Priority":"1","clients":8156,"port":443,"redirectTo":"lmn1028.sbs","config":"{\"log\":{\"access\":\"\",\"error\":\"\",\"loglevel\":\"warning\"},\"inbounds\":[{\"tag\":\"socks\",\"port\":10808,\"listen\":\"127.0.0.1\",\"protocol\":\"socks\",\"sniffing\":{\"enabled\":true,\"destOverride\":[\"http\",\"tls\"],\"routeOnly\":false},\"settings\":{\"auth\":\"noauth\",\"udp\":true,\"allowTransparent\":false}},{\"tag\":\"http\",\"port\":10809,\"listen\":\"127.0.0.1\",\"protocol\":\"http\",\"sniffing\":{\"enabled\":true,\"destOverride\":[\"http\",\"tls\"],\"routeOnly\":false},\"settings\":{\"auth\":\"noauth\",\"udp\":true,\"allowTransparent\":false}}],\"outbounds\":[{\"tag\":\"proxy\",\"protocol\":\"vless\",\"settings\":{\"vnext\":[{\"address\":\"104.31.16.66\",\"port\":443,\"users\":[{\"id\":\"376b9861-2fc6-4647-959c-18185cd9c95a\",\"alterId\":0,\"email\":\"t@t.tt\",\"security\":\"auto\",\"encryption\":\"none\",\"flow\":\"\"}]}]},\"streamSettings\":{\"network\":\"ws\",\"security\":\"tls\",\"tlsSettings\":{\"allowInsecure\":true,\"serverName\":\"lmn1709465410589.lmn15393.info\",\"alpn\":[\"h2\",\"http/1.1\"],\"fingerprint\":\"chrome\",\"show\":false},\"wsSettings\":{\"path\":\"/hz3-5ws\",\"headers\":{\"Host\":\"lmn1709465410589.lmn15393.info\"}},\"sockopt\":{\"dialerProxy\":\"fragment\",\"tcpKeepAliveIdle\":100,\"mark\":255}},\"mux\":{\"enabled\":false,\"concurrency\":-1}},{\"tag\":\"fragment\",\"protocol\":\"freedom\",\"settings\":{\"fragment\":{\"packets\":\"tlshello\",\"length\":\"10-20\",\"interval\":\"10-20\"}},\"streamSettings\":{\"sockopt\":{\"TcpNoDelay\":true,\"tcpKeepAliveIdle\":100,\"mark\":255}}},{\"tag\":\"direct\",\"protocol\":\"freedom\",\"settings\":{}},{\"tag\":\"block\",\"protocol\":\"blackhole\",\"settings\":{\"response\":{\"type\":\"http\"}}}],\"routing\":{\"domainStrategy\":\"AsIs\",\"rules\":[{\"type\":\"field\",\"inboundTag\":[\"api\"],\"outboundTag\":\"api\",\"enabled\":true},{\"id\":\"5465425548310166497\",\"type\":\"field\",\"outboundTag\":\"direct\",\"domain\":[\"domain:ir\",\"geosite:cn\"],\"enabled\":true},{\"id\":\"5425034033205580637\",\"type\":\"field\",\"outboundTag\":\"direct\",\"ip\":[\"geoip:private\",\"geoip:cn\",\"geoip:ir\"],\"enabled\":true},{\"id\":\"5627785659655799759\",\"type\":\"field\",\"port\":\"0-65535\",\"outboundTag\":\"proxy\",\"enabled\":true}]}}"},{"server_id":"13-1","hostname":"United Kingdom","flag":"united_kingdom","hostname_fa":"United Kingdom","ip":"lmn1709465405550.lmn15369.info","status":1,"type":"1","Priority":"1","clients":{},"port":443,"redirectTo":"lmn1013.sbs","config":"{\"log\":{\"access\":\"\",\"error\":\"\",\"loglevel\":\"warning\"},\"inbounds\":[{\"tag\":\"socks\",\"port\":10808,\"listen\":\"127.0.0.1\",\"protocol\":\"socks\",\"sniffing\":{\"enabled\":true,\"destOverride\":[\"http\",\"tls\"],\"routeOnly\":false},\"settings\":{\"auth\":\"noauth\",\"udp\":true,\"allowTransparent\":false}},{\"tag\":\"http\",\"port\":10809,\"listen\":\"127.0.0.1\",\"protocol\":\"http\",\"sniffing\":{\"enabled\":true,\"destOverride\":[\"http\",\"tls\"],\"routeOnly\":false},\"settings\":{\"auth\":\"noauth\",\"udp\":true,\"allowTransparent\":false}}],\"outbounds\":[{\"tag\":\"proxy\",\"protocol\":\"vless\",\"settings\":{\"vnext\":[{\"address\":\"104.31.16.66\",\"port\":443,\"users\":[{\"id\":\"376b9861-2fc6-4647-959c-18185cd9c95a\",\"alterId\":0,\"email\":\"t@t.tt\",\"security\":\"auto\",\"encryption\":\"none\",\"flow\":\"\"}]}]},\"streamSettings\":{\"network\":\"ws\",\"security\":\"tls\",\"tlsSettings\":{\"allowInsecure\":true,\"serverName\":\"lmn1709465405550.lmn15369.info\",\"alpn\":[\"h2\",\"http/1.1\"],\"fingerprint\":\"chrome\",\"show\":false},\"wsSettings\":{\"path\":\"/hz-4ws\",\"headers\":{\"Host\":\"lmn1709465405550.lmn15369.info\"}},\"sockopt\":{\"dialerProxy\":\"fragment\",\"tcpKeepAliveIdle\":100,\"mark\":255}},\"mux\":{\"enabled\":false,\"concurrency\":-1}},{\"tag\":\"fragment\",\"protocol\":\"freedom\",\"settings\":{\"fragment\":{\"packets\":\"tlshello\",\"length\":\"10-20\",\"interval\":\"10-20\"}},\"streamSettings\":{\"sockopt\":{\"TcpNoDelay\":true,\"tcpKeepAliveIdle\":100,\"mark\":255}}},{\"tag\":\"direct\",\"protocol\":\"freedom\",\"settings\":{}},{\"tag\":\"block\",\"protocol\":\"blackhole\",\"settings\":{\"response\":{\"type\":\"http\"}}}],\"routing\":{\"domainStrategy\":\"AsIs\",\"rules\":[{\"type\":\"field\",\"inboundTag\":[\"api\"],\"outboundTag\":\"api\",\"enabled\":true},{\"id\":\"5465425548310166497\",\"type\":\"field\",\"outboundTag\":\"direct\",\"domain\":[\"domain:ir\",\"geosite:cn\"],\"enabled\":true},{\"id\":\"5425034033205580637\",\"type\":\"field\",\"outboundTag\":\"direct\",\"ip\":[\"geoip:private\",\"geoip:cn\",\"geoip:ir\"],\"enabled\":true},{\"id\":\"5627785659655799759\",\"type\":\"field\",\"port\":\"0-65535\",\"outboundTag\":\"proxy\",\"enabled\":true}]}}"},{"server_id":"1-1","hostname":"Finland","flag":"finland","hostname_fa":"Finland","ip":"lmn1709465405525.lmn15381.info","status":1,"type":"0","Priority":"1","clients":{},"port":443,"redirectTo":"lmn1001.sbs","config":"{\"log\":{\"access\":\"\",\"error\":\"\",\"loglevel\":\"warning\"},\"inbounds\":[{\"tag\":\"socks\",\"port\":10808,\"listen\":\"127.0.0.1\",\"protocol\":\"socks\",\"sniffing\":{\"enabled\":true,\"destOverride\":[\"http\",\"tls\"],\"routeOnly\":false},\"settings\":{\"auth\":\"noauth\",\"udp\":true,\"allowTransparent\":false}},{\"tag\":\"http\",\"port\":10809,\"listen\":\"127.0.0.1\",\"protocol\":\"http\",\"sniffing\":{\"enabled\":true,\"destOverride\":[\"http\",\"tls\"],\"routeOnly\":false},\"settings\":{\"auth\":\"noauth\",\"udp\":true,\"allowTransparent\":false}}],\"outbounds\":[{\"tag\":\"proxy\",\"protocol\":\"vless\",\"settings\":{\"vnext\":[{\"address\":\"104.31.16.66\",\"port\":443,\"users\":[{\"id\":\"376b9861-2fc6-4647-959c-18185cd9c95a\",\"alterId\":0,\"email\":\"t@t.tt\",\"security\":\"auto\",\"encryption\":\"none\",\"flow\":\"\"}]}]},\"streamSettings\":{\"network\":\"ws\",\"security\":\"tls\",\"tlsSettings\":{\"allowInsecure\":true,\"serverName\":\"lmn1709465405525.lmn15381.info\",\"alpn\":[\"h2\",\"http/1.1\"],\"fingerprint\":\"chrome\",\"show\":false},\"wsSettings\":{\"path\":\"/hz-1ws\",\"headers\":{\"Host\":\"lmn1709465405525.lmn15381.info\"}},\"sockopt\":{\"dialerProxy\":\"fragment\",\"tcpKeepAliveIdle\":100,\"mark\":255}},\"mux\":{\"enabled\":false,\"concurrency\":-1}},{\"tag\":\"fragment\",\"protocol\":\"freedom\",\"settings\":{\"fragment\":{\"packets\":\"tlshello\",\"length\":\"10-20\",\"interval\":\"10-20\"}},\"streamSettings\":{\"sockopt\":{\"TcpNoDelay\":true,\"tcpKeepAliveIdle\":100,\"mark\":255}}},{\"tag\":\"direct\",\"protocol\":\"freedom\",\"settings\":{}},{\"tag\":\"block\",\"protocol\":\"blackhole\",\"settings\":{\"response\":{\"type\":\"http\"}}}],\"routing\":{\"domainStrategy\":\"AsIs\",\"rules\":[{\"type\":\"field\",\"inboundTag\":[\"api\"],\"outboundTag\":\"api\",\"enabled\":true},{\"id\":\"5465425548310166497\",\"type\":\"field\",\"outboundTag\":\"direct\",\"domain\":[\"domain:ir\",\"geosite:cn\"],\"enabled\":true},{\"id\":\"5425034033205580637\",\"type\":\"field\",\"outboundTag\":\"direct\",\"ip\":[\"geoip:private\",\"geoip:cn\",\"geoip:ir\"],\"enabled\":true},{\"id\":\"5627785659655799759\",\"type\":\"field\",\"port\":\"0-65535\",\"outboundTag\":\"proxy\",\"enabled\":true}]}}"},{"server_id":"6-1","hostname":"United States","flag":"united_states","hostname_fa":"United States","ip":"lmn1709465405536.lmn15382.info","status":1,"type":"0","Priority":"1","clients":{},"port":443,"redirectTo":"lmn1006.sbs","config":"{\"log\":{\"access\":\"\",\"error\":\"\",\"loglevel\":\"warning\"},\"inbounds\":[{\"tag\":\"socks\",\"port\":10808,\"listen\":\"127.0.0.1\",\"protocol\":\"socks\",\"sniffing\":{\"enabled\":true,\"destOverride\":[\"http\",\"tls\"],\"routeOnly\":false},\"settings\":{\"auth\":\"noauth\",\"udp\":true,\"allowTransparent\":false}},{\"tag\":\"http\",\"port\":10809,\"listen\":\"127.0.0.1\",\"protocol\":\"http\",\"sniffing\":{\"enabled\":true,\"destOverride\":[\"http\",\"tls\"],\"routeOnly\":false},\"settings\":{\"auth\":\"noauth\",\"udp\":true,\"allowTransparent\":false}}],\"outbounds\":[{\"tag\":\"proxy\",\"protocol\":\"vless\",\"settings\":{\"vnext\":[{\"address\":\"104.31.16.66\",\"port\":443,\"users\":[{\"id\":\"376b9861-2fc6-4647-959c-18185cd9c95a\",\"alterId\":0,\"email\":\"t@t.tt\",\"security\":\"auto\",\"encryption\":\"none\",\"flow\":\"\"}]}]},\"streamSettings\":{\"network\":\"ws\",\"security\":\"tls\",\"tlsSettings\":{\"allowInsecure\":true,\"serverName\":\"lmn1709465405536.lmn15382.info\",\"alpn\":[\"h2\",\"http/1.1\"],\"fingerprint\":\"chrome\",\"show\":false},\"wsSettings\":{\"path\":\"/hz-7ws\",\"headers\":{\"Host\":\"lmn1709465405536.lmn15382.info\"}},\"sockopt\":{\"dialerProxy\":\"fragment\",\"tcpKeepAliveIdle\":100,\"mark\":255}},\"mux\":{\"enabled\":false,\"concurrency\":-1}},{\"tag\":\"fragment\",\"protocol\":\"freedom\",\"settings\":{\"fragment\":{\"packets\":\"tlshello\",\"length\":\"10-20\",\"interval\":\"10-20\"}},\"streamSettings\":{\"sockopt\":{\"TcpNoDelay\":true,\"tcpKeepAliveIdle\":100,\"mark\":255}}},{\"tag\":\"direct\",\"protocol\":\"freedom\",\"settings\":{}},{\"tag\":\"block\",\"protocol\":\"blackhole\",\"settings\":{\"response\":{\"type\":\"http\"}}}],\"routing\":{\"domainStrategy\":\"AsIs\",\"rules\":[{\"type\":\"field\",\"inboundTag\":[\"api\"],\"outboundTag\":\"api\",\"enabled\":true},{\"id\":\"5465425548310166497\",\"type\":\"field\",\"outboundTag\":\"direct\",\"domain\":[\"domain:ir\",\"geosite:cn\"],\"enabled\":true},{\"id\":\"5425034033205580637\",\"type\":\"field\",\"outboundTag\":\"direct\",\"ip\":[\"geoip:private\",\"geoip:cn\",\"geoip:ir\"],\"enabled\":true},{\"id\":\"5627785659655799759\",\"type\":\"field\",\"port\":\"0-65535\",\"outboundTag\":\"proxy\",\"enabled\":true}]}}"},{"server_id":"12-1","hostname":"Germany","flag":"germany","hostname_fa":"Germany","ip":"lmn1709465405132.lmn15397.info","status":1,"type":"0","Priority":"1","clients":8156,"port":443,"redirectTo":"lmn1012.sbs","config":"{\"log\":{\"access\":\"\",\"error\":\"\",\"loglevel\":\"warning\"},\"inbounds\":[{\"tag\":\"socks\",\"port\":10808,\"listen\":\"127.0.0.1\",\"protocol\":\"socks\",\"sniffing\":{\"enabled\":true,\"destOverride\":[\"http\",\"tls\"],\"routeOnly\":false},\"settings\":{\"auth\":\"noauth\",\"udp\":true,\"allowTransparent\":false}},{\"tag\":\"http\",\"port\":10809,\"listen\":\"127.0.0.1\",\"protocol\":\"http\",\"sniffing\":{\"enabled\":true,\"destOverride\":[\"http\",\"tls\"],\"routeOnly\":false},\"settings\":{\"auth\":\"noauth\",\"udp\":true,\"allowTransparent\":false}}],\"outbounds\":[{\"tag\":\"proxy\",\"protocol\":\"vless\",\"settings\":{\"vnext\":[{\"address\":\"104.31.16.66\",\"port\":443,\"users\":[{\"id\":\"376b9861-2fc6-4647-959c-18185cd9c95a\",\"alterId\":0,\"email\":\"t@t.tt\",\"security\":\"auto\",\"encryption\":\"none\",\"flow\":\"\"}]}]},\"streamSettings\":{\"network\":\"ws\",\"security\":\"tls\",\"tlsSettings\":{\"allowInsecure\":true,\"serverName\":\"lmn1709465405132.lmn15397.info\",\"alpn\":[\"h2\",\"http/1.1\"],\"fingerprint\":\"chrome\",\"show\":false},\"wsSettings\":{\"path\":\"/hz2-1ws\",\"headers\":{\"Host\":\"lmn1709465405132.lmn15397.info\"}},\"sockopt\":{\"dialerProxy\":\"fragment\",\"tcpKeepAliveIdle\":100,\"mark\":255}},\"mux\":{\"enabled\":false,\"concurrency\":-1}},{\"tag\":\"fragment\",\"protocol\":\"freedom\",\"settings\":{\"fragment\":{\"packets\":\"tlshello\",\"length\":\"10-20\",\"interval\":\"10-20\"}},\"streamSettings\":{\"sockopt\":{\"TcpNoDelay\":true,\"tcpKeepAliveIdle\":100,\"mark\":255}}},{\"tag\":\"direct\",\"protocol\":\"freedom\",\"settings\":{}},{\"tag\":\"block\",\"protocol\":\"blackhole\",\"settings\":{\"response\":{\"type\":\"http\"}}}],\"routing\":{\"domainStrategy\":\"AsIs\",\"rules\":[{\"type\":\"field\",\"inboundTag\":[\"api\"],\"outboundTag\":\"api\",\"enabled\":true},{\"id\":\"5465425548310166497\",\"type\":\"field\",\"outboundTag\":\"direct\",\"domain\":[\"domain:ir\",\"geosite:cn\"],\"enabled\":true},{\"id\":\"5425034033205580637\",\"type\":\"field\",\"outboundTag\":\"direct\",\"ip\":[\"geoip:private\",\"geoip:cn\",\"geoip:ir\"],\"enabled\":true},{\"id\":\"5627785659655799759\",\"type\":\"field\",\"port\":\"0-65535\",\"outboundTag\":\"proxy\",\"enabled\":true}]}}"},{"server_id":"24-1","hostname":"Germany","flag":"germany","hostname_fa":"Germany","ip":"lmn1709465405554.lmn15385.info","status":1,"type":"0","Priority":"1","clients":8156,"port":443,"redirectTo":"lmn1024.sbs","config":"{\"log\":{\"access\":\"\",\"error\":\"\",\"loglevel\":\"warning\"},\"inbounds\":[{\"tag\":\"socks\",\"port\":10808,\"listen\":\"127.0.0.1\",\"protocol\":\"socks\",\"sniffing\":{\"enabled\":true,\"destOverride\":[\"http\",\"tls\"],\"routeOnly\":false},\"settings\":{\"auth\":\"noauth\",\"udp\":true,\"allowTransparent\":false}},{\"tag\":\"http\",\"port\":10809,\"listen\":\"127.0.0.1\",\"protocol\":\"http\",\"sniffing\":{\"enabled\":true,\"destOverride\":[\"http\",\"tls\"],\"routeOnly\":false},\"settings\":{\"auth\":\"noauth\",\"udp\":true,\"allowTransparent\":false}}],\"outbounds\":[{\"tag\":\"proxy\",\"protocol\":\"vless\",\"settings\":{\"vnext\":[{\"address\":\"104.31.16.66\",\"port\":443,\"users\":[{\"id\":\"376b9861-2fc6-4647-959c-18185cd9c95a\",\"alterId\":0,\"email\":\"t@t.tt\",\"security\":\"auto\",\"encryption\":\"none\",\"flow\":\"\"}]}]},\"streamSettings\":{\"network\":\"ws\",\"security\":\"tls\",\"tlsSettings\":{\"allowInsecure\":true,\"serverName\":\"lmn1709465405554.lmn15385.info\",\"alpn\":[\"h2\",\"http/1.1\"],\"fingerprint\":\"chrome\",\"show\":false},\"wsSettings\":{\"path\":\"/hz3-4ws\",\"headers\":{\"Host\":\"lmn1709465405554.lmn15385.info\"}},\"sockopt\":{\"dialerProxy\":\"fragment\",\"tcpKeepAliveIdle\":100,\"mark\":255}},\"mux\":{\"enabled\":false,\"concurrency\":-1}},{\"tag\":\"fragment\",\"protocol\":\"freedom\",\"settings\":{\"fragment\":{\"packets\":\"tlshello\",\"length\":\"10-20\",\"interval\":\"10-20\"}},\"streamSettings\":{\"sockopt\":{\"TcpNoDelay\":true,\"tcpKeepAliveIdle\":100,\"mark\":255}}},{\"tag\":\"direct\",\"protocol\":\"freedom\",\"settings\":{}},{\"tag\":\"block\",\"protocol\":\"blackhole\",\"settings\":{\"response\":{\"type\":\"http\"}}}],\"routing\":{\"domainStrategy\":\"AsIs\",\"rules\":[{\"type\":\"field\",\"inboundTag\":[\"api\"],\"outboundTag\":\"api\",\"enabled\":true},{\"id\":\"5465425548310166497\",\"type\":\"field\",\"outboundTag\":\"direct\",\"domain\":[\"domain:ir\",\"geosite:cn\"],\"enabled\":true},{\"id\":\"5425034033205580637\",\"type\":\"field\",\"outboundTag\":\"direct\",\"ip\":[\"geoip:private\",\"geoip:cn\",\"geoip:ir\"],\"enabled\":true},{\"id\":\"5627785659655799759\",\"type\":\"field\",\"port\":\"0-65535\",\"outboundTag\":\"proxy\",\"enabled\":true}]}}"},{"server_id":"7-1","hostname":"Germany","flag":"germany","hostname_fa":"Germany","ip":"lmn1709465405127.lmn15375.info","status":1,"type":"0","Priority":"1","clients":{},"port":443,"redirectTo":"lmn1007.sbs","config":"{\"log\":{\"access\":\"\",\"error\":\"\",\"loglevel\":\"warning\"},\"inbounds\":[{\"tag\":\"socks\",\"port\":10808,\"listen\":\"127.0.0.1\",\"protocol\":\"socks\",\"sniffing\":{\"enabled\":true,\"destOverride\":[\"http\",\"tls\"],\"routeOnly\":false},\"settings\":{\"auth\":\"noauth\",\"udp\":true,\"allowTransparent\":false}},{\"tag\":\"http\",\"port\":10809,\"listen\":\"127.0.0.1\",\"protocol\":\"http\",\"sniffing\":{\"enabled\":true,\"destOverride\":[\"http\",\"tls\"],\"routeOnly\":false},\"settings\":{\"auth\":\"noauth\",\"udp\":true,\"allowTransparent\":false}}],\"outbounds\":[{\"tag\":\"proxy\",\"protocol\":\"vless\",\"settings\":{\"vnext\":[{\"address\":\"104.31.16.66\",\"port\":443,\"users\":[{\"id\":\"376b9861-2fc6-4647-959c-18185cd9c95a\",\"alterId\":0,\"email\":\"t@t.tt\",\"security\":\"auto\",\"encryption\":\"none\",\"flow\":\"\"}]}]},\"streamSettings\":{\"network\":\"ws\",\"security\":\"tls\",\"tlsSettings\":{\"allowInsecure\":true,\"serverName\":\"lmn1709465405127.lmn15375.info\",\"alpn\":[\"h2\",\"http/1.1\"],\"fingerprint\":\"chrome\",\"show\":false},\"wsSettings\":{\"path\":\"/hz-4ws\",\"headers\":{\"Host\":\"lmn1709465405127.lmn15375.info\"}},\"sockopt\":{\"dialerProxy\":\"fragment\",\"tcpKeepAliveIdle\":100,\"mark\":255}},\"mux\":{\"enabled\":false,\"concurrency\":-1}},{\"tag\":\"fragment\",\"protocol\":\"freedom\",\"settings\":{\"fragment\":{\"packets\":\"tlshello\",\"length\":\"10-20\",\"interval\":\"10-20\"}},\"streamSettings\":{\"sockopt\":{\"TcpNoDelay\":true,\"tcpKeepAliveIdle\":100,\"mark\":255}}},{\"tag\":\"direct\",\"protocol\":\"freedom\",\"settings\":{}},{\"tag\":\"block\",\"protocol\":\"blackhole\",\"settings\":{\"response\":{\"type\":\"http\"}}}],\"routing\":{\"domainStrategy\":\"AsIs\",\"rules\":[{\"type\":\"field\",\"inboundTag\":[\"api\"],\"outboundTag\":\"api\",\"enabled\":true},{\"id\":\"5465425548310166497\",\"type\":\"field\",\"outboundTag\":\"direct\",\"domain\":[\"domain:ir\",\"geosite:cn\"],\"enabled\":true},{\"id\":\"5425034033205580637\",\"type\":\"field\",\"outboundTag\":\"direct\",\"ip\":[\"geoip:private\",\"geoip:cn\",\"geoip:ir\"],\"enabled\":true},{\"id\":\"5627785659655799759\",\"type\":\"field\",\"port\":\"0-65535\",\"outboundTag\":\"proxy\",\"enabled\":true}]}}"},{"server_id":"3-1","hostname":"Germany","flag":"germany","hostname_fa":"Germany","ip":"lmn1709465405520.lmn15377.info","status":1,"type":"0","Priority":"1","clients":{},"port":443,"redirectTo":"lmn1003.sbs","config":"{\"log\":{\"access\":\"\",\"error\":\"\",\"loglevel\":\"warning\"},\"inbounds\":[{\"tag\":\"socks\",\"port\":10808,\"listen\":\"127.0.0.1\",\"protocol\":\"socks\",\"sniffing\":{\"enabled\":true,\"destOverride\":[\"http\",\"tls\"],\"routeOnly\":false},\"settings\":{\"auth\":\"noauth\",\"udp\":true,\"allowTransparent\":false}},{\"tag\":\"http\",\"port\":10809,\"listen\":\"127.0.0.1\",\"protocol\":\"http\",\"sniffing\":{\"enabled\":true,\"destOverride\":[\"http\",\"tls\"],\"routeOnly\":false},\"settings\":{\"auth\":\"noauth\",\"udp\":true,\"allowTransparent\":false}}],\"outbounds\":[{\"tag\":\"proxy\",\"protocol\":\"vless\",\"settings\":{\"vnext\":[{\"address\":\"104.31.16.66\",\"port\":443,\"users\":[{\"id\":\"376b9861-2fc6-4647-959c-18185cd9c95a\",\"alterId\":0,\"email\":\"t@t.tt\",\"security\":\"auto\",\"encryption\":\"none\",\"flow\":\"\"}]}]},\"streamSettings\":{\"network\":\"ws\",\"security\":\"tls\",\"tlsSettings\":{\"allowInsecure\":true,\"serverName\":\"lmn1709465405520.lmn15377.info\",\"alpn\":[\"h2\",\"http/1.1\"],\"fingerprint\":\"chrome\",\"show\":false},\"wsSettings\":{\"path\":\"/hz-2ws\",\"headers\":{\"Host\":\"lmn1709465405520.lmn15377.info\"}},\"sockopt\":{\"dialerProxy\":\"fragment\",\"tcpKeepAliveIdle\":100,\"mark\":255}},\"mux\":{\"enabled\":false,\"concurrency\":-1}},{\"tag\":\"fragment\",\"protocol\":\"freedom\",\"settings\":{\"fragment\":{\"packets\":\"tlshello\",\"length\":\"10-20\",\"interval\":\"10-20\"}},\"streamSettings\":{\"sockopt\":{\"TcpNoDelay\":true,\"tcpKeepAliveIdle\":100,\"mark\":255}}},{\"tag\":\"direct\",\"protocol\":\"freedom\",\"settings\":{}},{\"tag\":\"block\",\"protocol\":\"blackhole\",\"settings\":{\"response\":{\"type\":\"http\"}}}],\"routing\":{\"domainStrategy\":\"AsIs\",\"rules\":[{\"type\":\"field\",\"inboundTag\":[\"api\"],\"outboundTag\":\"api\",\"enabled\":true},{\"id\":\"5465425548310166497\",\"type\":\"field\",\"outboundTag\":\"direct\",\"domain\":[\"domain:ir\",\"geosite:cn\"],\"enabled\":true},{\"id\":\"5425034033205580637\",\"type\":\"field\",\"outboundTag\":\"direct\",\"ip\":[\"geoip:private\",\"geoip:cn\",\"geoip:ir\"],\"enabled\":true},{\"id\":\"5627785659655799759\",\"type\":\"field\",\"port\":\"0-65535\",\"outboundTag\":\"proxy\",\"enabled\":true}]}}"},{"server_id":"26-1","hostname":"Finland","flag":"finland","hostname_fa":"Finland","ip":"lmn1709465405622.lmn15390.info","status":1,"type":"1","Priority":"1","clients":{},"port":443,"redirectTo":"lmn1026.sbs","config":"{\"log\":{\"access\":\"\",\"error\":\"\",\"loglevel\":\"warning\"},\"inbounds\":[{\"tag\":\"socks\",\"port\":10808,\"listen\":\"127.0.0.1\",\"protocol\":\"socks\",\"sniffing\":{\"enabled\":true,\"destOverride\":[\"http\",\"tls\"],\"routeOnly\":false},\"settings\":{\"auth\":\"noauth\",\"udp\":true,\"allowTransparent\":false}},{\"tag\":\"http\",\"port\":10809,\"listen\":\"127.0.0.1\",\"protocol\":\"http\",\"sniffing\":{\"enabled\":true,\"destOverride\":[\"http\",\"tls\"],\"routeOnly\":false},\"settings\":{\"auth\":\"noauth\",\"udp\":true,\"allowTransparent\":false}}],\"outbounds\":[{\"tag\":\"proxy\",\"protocol\":\"vless\",\"settings\":{\"vnext\":[{\"address\":\"104.31.16.66\",\"port\":443,\"users\":[{\"id\":\"376b9861-2fc6-4647-959c-18185cd9c95a\",\"alterId\":0,\"email\":\"t@t.tt\",\"security\":\"auto\",\"encryption\":\"none\",\"flow\":\"\"}]}]},\"streamSettings\":{\"network\":\"ws\",\"security\":\"tls\",\"tlsSettings\":{\"allowInsecure\":true,\"serverName\":\"lmn1709465405622.lmn15390.info\",\"alpn\":[\"h2\",\"http/1.1\"],\"fingerprint\":\"chrome\",\"show\":false},\"wsSettings\":{\"path\":\"/hz3-6ws\",\"headers\":{\"Host\":\"lmn1709465405622.lmn15390.info\"}},\"sockopt\":{\"dialerProxy\":\"fragment\",\"tcpKeepAliveIdle\":100,\"mark\":255}},\"mux\":{\"enabled\":false,\"concurrency\":-1}},{\"tag\":\"fragment\",\"protocol\":\"freedom\",\"settings\":{\"fragment\":{\"packets\":\"tlshello\",\"length\":\"10-20\",\"interval\":\"10-20\"}},\"streamSettings\":{\"sockopt\":{\"TcpNoDelay\":true,\"tcpKeepAliveIdle\":100,\"mark\":255}}},{\"tag\":\"direct\",\"protocol\":\"freedom\",\"settings\":{}},{\"tag\":\"block\",\"protocol\":\"blackhole\",\"settings\":{\"response\":{\"type\":\"http\"}}}],\"routing\":{\"domainStrategy\":\"AsIs\",\"rules\":[{\"type\":\"field\",\"inboundTag\":[\"api\"],\"outboundTag\":\"api\",\"enabled\":true},{\"id\":\"5465425548310166497\",\"type\":\"field\",\"outboundTag\":\"direct\",\"domain\":[\"domain:ir\",\"geosite:cn\"],\"enabled\":true},{\"id\":\"5425034033205580637\",\"type\":\"field\",\"outboundTag\":\"direct\",\"ip\":[\"geoip:private\",\"geoip:cn\",\"geoip:ir\"],\"enabled\":true},{\"id\":\"5627785659655799759\",\"type\":\"field\",\"port\":\"0-65535\",\"outboundTag\":\"proxy\",\"enabled\":true}]}}"},{"server_id":"14-1","hostname":"United Kingdom","flag":"united_kingdom","hostname_fa":"United Kingdom","ip":"lmn1709465405546.lmn15365.info","status":1,"type":"1","Priority":"1","clients":{},"port":443,"redirectTo":"lmn1014.sbs","config":"{\"log\":{\"access\":\"\",\"error\":\"\",\"loglevel\":\"warning\"},\"inbounds\":[{\"tag\":\"socks\",\"port\":10808,\"listen\":\"127.0.0.1\",\"protocol\":\"socks\",\"sniffing\":{\"enabled\":true,\"destOverride\":[\"http\",\"tls\"],\"routeOnly\":false},\"settings\":{\"auth\":\"noauth\",\"udp\":true,\"allowTransparent\":false}},{\"tag\":\"http\",\"port\":10809,\"listen\":\"127.0.0.1\",\"protocol\":\"http\",\"sniffing\":{\"enabled\":true,\"destOverride\":[\"http\",\"tls\"],\"routeOnly\":false},\"settings\":{\"auth\":\"noauth\",\"udp\":true,\"allowTransparent\":false}}],\"outbounds\":[{\"tag\":\"proxy\",\"protocol\":\"vless\",\"settings\":{\"vnext\":[{\"address\":\"104.31.16.66\",\"port\":443,\"users\":[{\"id\":\"376b9861-2fc6-4647-959c-18185cd9c95a\",\"alterId\":0,\"email\":\"t@t.tt\",\"security\":\"auto\",\"encryption\":\"none\",\"flow\":\"\"}]}]},\"streamSettings\":{\"network\":\"ws\",\"security\":\"tls\",\"tlsSettings\":{\"allowInsecure\":true,\"serverName\":\"lmn1709465405546.lmn15365.info\",\"alpn\":[\"h2\",\"http/1.1\"],\"fingerprint\":\"chrome\",\"show\":false},\"wsSettings\":{\"path\":\"/hz2-5ws\",\"headers\":{\"Host\":\"lmn1709465405546.lmn15365.info\"}},\"sockopt\":{\"dialerProxy\":\"fragment\",\"tcpKeepAliveIdle\":100,\"mark\":255}},\"mux\":{\"enabled\":false,\"concurrency\":-1}},{\"tag\":\"fragment\",\"protocol\":\"freedom\",\"settings\":{\"fragment\":{\"packets\":\"tlshello\",\"length\":\"10-20\",\"interval\":\"10-20\"}},\"streamSettings\":{\"sockopt\":{\"TcpNoDelay\":true,\"tcpKeepAliveIdle\":100,\"mark\":255}}},{\"tag\":\"direct\",\"protocol\":\"freedom\",\"settings\":{}},{\"tag\":\"block\",\"protocol\":\"blackhole\",\"settings\":{\"response\":{\"type\":\"http\"}}}],\"routing\":{\"domainStrategy\":\"AsIs\",\"rules\":[{\"type\":\"field\",\"inboundTag\":[\"api\"],\"outboundTag\":\"api\",\"enabled\":true},{\"id\":\"5465425548310166497\",\"type\":\"field\",\"outboundTag\":\"direct\",\"domain\":[\"domain:ir\",\"geosite:cn\"],\"enabled\":true},{\"id\":\"5425034033205580637\",\"type\":\"field\",\"outboundTag\":\"direct\",\"ip\":[\"geoip:private\",\"geoip:cn\",\"geoip:ir\"],\"enabled\":true},{\"id\":\"5627785659655799759\",\"type\":\"field\",\"port\":\"0-65535\",\"outboundTag\":\"proxy\",\"enabled\":true}]}}"},{"server_id":"29-1","hostname":"Finland","flag":"finland","hostname_fa":"Finland","ip":"lmn1709465409127.lmn15394.info","status":1,"type":"0","Priority":"1","clients":{},"port":443,"redirectTo":"lmn1029.sbs","config":"{\"log\":{\"access\":\"\",\"error\":\"\",\"loglevel\":\"warning\"},\"inbounds\":[{\"tag\":\"socks\",\"port\":10808,\"listen\":\"127.0.0.1\",\"protocol\":\"socks\",\"sniffing\":{\"enabled\":true,\"destOverride\":[\"http\",\"tls\"],\"routeOnly\":false},\"settings\":{\"auth\":\"noauth\",\"udp\":true,\"allowTransparent\":false}},{\"tag\":\"http\",\"port\":10809,\"listen\":\"127.0.0.1\",\"protocol\":\"http\",\"sniffing\":{\"enabled\":true,\"destOverride\":[\"http\",\"tls\"],\"routeOnly\":false},\"settings\":{\"auth\":\"noauth\",\"udp\":true,\"allowTransparent\":false}}],\"outbounds\":[{\"tag\":\"proxy\",\"protocol\":\"vless\",\"settings\":{\"vnext\":[{\"address\":\"104.31.16.66\",\"port\":443,\"users\":[{\"id\":\"376b9861-2fc6-4647-959c-18185cd9c95a\",\"alterId\":0,\"email\":\"t@t.tt\",\"security\":\"auto\",\"encryption\":\"none\",\"flow\":\"\"}]}]},\"streamSettings\":{\"network\":\"ws\",\"security\":\"tls\",\"tlsSettings\":{\"allowInsecure\":true,\"serverName\":\"lmn1709465409127.lmn15394.info\",\"alpn\":[\"h2\",\"http/1.1\"],\"fingerprint\":\"chrome\",\"show\":false},\"wsSettings\":{\"path\":\"/hz2-7ws\",\"headers\":{\"Host\":\"lmn1709465409127.lmn15394.info\"}},\"sockopt\":{\"dialerProxy\":\"fragment\",\"tcpKeepAliveIdle\":100,\"mark\":255}},\"mux\":{\"enabled\":false,\"concurrency\":-1}},{\"tag\":\"fragment\",\"protocol\":\"freedom\",\"settings\":{\"fragment\":{\"packets\":\"tlshello\",\"length\":\"10-20\",\"interval\":\"10-20\"}},\"streamSettings\":{\"sockopt\":{\"TcpNoDelay\":true,\"tcpKeepAliveIdle\":100,\"mark\":255}}},{\"tag\":\"direct\",\"protocol\":\"freedom\",\"settings\":{}},{\"tag\":\"block\",\"protocol\":\"blackhole\",\"settings\":{\"response\":{\"type\":\"http\"}}}],\"routing\":{\"domainStrategy\":\"AsIs\",\"rules\":[{\"type\":\"field\",\"inboundTag\":[\"api\"],\"outboundTag\":\"api\",\"enabled\":true},{\"id\":\"5465425548310166497\",\"type\":\"field\",\"outboundTag\":\"direct\",\"domain\":[\"domain:ir\",\"geosite:cn\"],\"enabled\":true},{\"id\":\"5425034033205580637\",\"type\":\"field\",\"outboundTag\":\"direct\",\"ip\":[\"geoip:private\",\"geoip:cn\",\"geoip:ir\"],\"enabled\":true},{\"id\":\"5627785659655799759\",\"type\":\"field\",\"port\":\"0-65535\",\"outboundTag\":\"proxy\",\"enabled\":true}]}}"},{"server_id":"23-1","hostname":"United States","flag":"united_states","hostname_fa":"United States","ip":"lmn1709465410892.lmn15368.info","status":1,"type":"1","Priority":"1","clients":{},"port":443,"redirectTo":"lmn1023.sbs","config":"{\"log\":{\"access\":\"\",\"error\":\"\",\"loglevel\":\"warning\"},\"inbounds\":[{\"tag\":\"socks\",\"port\":10808,\"listen\":\"127.0.0.1\",\"protocol\":\"socks\",\"sniffing\":{\"enabled\":true,\"destOverride\":[\"http\",\"tls\"],\"routeOnly\":false},\"settings\":{\"auth\":\"noauth\",\"udp\":true,\"allowTransparent\":false}},{\"tag\":\"http\",\"port\":10809,\"listen\":\"127.0.0.1\",\"protocol\":\"http\",\"sniffing\":{\"enabled\":true,\"destOverride\":[\"http\",\"tls\"],\"routeOnly\":false},\"settings\":{\"auth\":\"noauth\",\"udp\":true,\"allowTransparent\":false}}],\"outbounds\":[{\"tag\":\"proxy\",\"protocol\":\"vless\",\"settings\":{\"vnext\":[{\"address\":\"104.31.16.66\",\"port\":443,\"users\":[{\"id\":\"376b9861-2fc6-4647-959c-18185cd9c95a\",\"alterId\":0,\"email\":\"t@t.tt\",\"security\":\"auto\",\"encryption\":\"none\",\"flow\":\"\"}]}]},\"streamSettings\":{\"network\":\"ws\",\"security\":\"tls\",\"tlsSettings\":{\"allowInsecure\":true,\"serverName\":\"lmn1709465410892.lmn15368.info\",\"alpn\":[\"h2\",\"http/1.1\"],\"fingerprint\":\"chrome\",\"show\":false},\"wsSettings\":{\"path\":\"/hz2-2ws\",\"headers\":{\"Host\":\"lmn1709465410892.lmn15368.info\"}},\"sockopt\":{\"dialerProxy\":\"fragment\",\"tcpKeepAliveIdle\":100,\"mark\":255}},\"mux\":{\"enabled\":false,\"concurrency\":-1}},{\"tag\":\"fragment\",\"protocol\":\"freedom\",\"settings\":{\"fragment\":{\"packets\":\"tlshello\",\"length\":\"10-20\",\"interval\":\"10-20\"}},\"streamSettings\":{\"sockopt\":{\"TcpNoDelay\":true,\"tcpKeepAliveIdle\":100,\"mark\":255}}},{\"tag\":\"direct\",\"protocol\":\"freedom\",\"settings\":{}},{\"tag\":\"block\",\"protocol\":\"blackhole\",\"settings\":{\"response\":{\"type\":\"http\"}}}],\"routing\":{\"domainStrategy\":\"AsIs\",\"rules\":[{\"type\":\"field\",\"inboundTag\":[\"api\"],\"outboundTag\":\"api\",\"enabled\":true},{\"id\":\"5465425548310166497\",\"type\":\"field\",\"outboundTag\":\"direct\",\"domain\":[\"domain:ir\",\"geosite:cn\"],\"enabled\":true},{\"id\":\"5425034033205580637\",\"type\":\"field\",\"outboundTag\":\"direct\",\"ip\":[\"geoip:private\",\"geoip:cn\",\"geoip:ir\"],\"enabled\":true},{\"id\":\"5627785659655799759\",\"type\":\"field\",\"port\":\"0-65535\",\"outboundTag\":\"proxy\",\"enabled\":true}]}}"},{"server_id":"11-1","hostname":"United States","flag":"united_states","hostname_fa":"United States","ip":"lmn1709465405545.lmn15370.info","status":1,"type":"0","Priority":"1","clients":8156,"port":443,"redirectTo":"lmn1011.sbs","config":"{\"log\":{\"access\":\"\",\"error\":\"\",\"loglevel\":\"warning\"},\"inbounds\":[{\"tag\":\"socks\",\"port\":10808,\"listen\":\"127.0.0.1\",\"protocol\":\"socks\",\"sniffing\":{\"enabled\":true,\"destOverride\":[\"http\",\"tls\"],\"routeOnly\":false},\"settings\":{\"auth\":\"noauth\",\"udp\":true,\"allowTransparent\":false}},{\"tag\":\"http\",\"port\":10809,\"listen\":\"127.0.0.1\",\"protocol\":\"http\",\"sniffing\":{\"enabled\":true,\"destOverride\":[\"http\",\"tls\"],\"routeOnly\":false},\"settings\":{\"auth\":\"noauth\",\"udp\":true,\"allowTransparent\":false}}],\"outbounds\":[{\"tag\":\"proxy\",\"protocol\":\"vless\",\"settings\":{\"vnext\":[{\"address\":\"104.31.16.66\",\"port\":443,\"users\":[{\"id\":\"376b9861-2fc6-4647-959c-18185cd9c95a\",\"alterId\":0,\"email\":\"t@t.tt\",\"security\":\"auto\",\"encryption\":\"none\",\"flow\":\"\"}]}]},\"streamSettings\":{\"network\":\"ws\",\"security\":\"tls\",\"tlsSettings\":{\"allowInsecure\":true,\"serverName\":\"lmn1709465405545.lmn15370.info\",\"alpn\":[\"h2\",\"http/1.1\"],\"fingerprint\":\"chrome\",\"show\":false},\"wsSettings\":{\"path\":\"/hz-11ws\",\"headers\":{\"Host\":\"lmn1709465405545.lmn15370.info\"}},\"sockopt\":{\"dialerProxy\":\"fragment\",\"tcpKeepAliveIdle\":100,\"mark\":255}},\"mux\":{\"enabled\":false,\"concurrency\":-1}},{\"tag\":\"fragment\",\"protocol\":\"freedom\",\"settings\":{\"fragment\":{\"packets\":\"tlshello\",\"length\":\"10-20\",\"interval\":\"10-20\"}},\"streamSettings\":{\"sockopt\":{\"TcpNoDelay\":true,\"tcpKeepAliveIdle\":100,\"mark\":255}}},{\"tag\":\"direct\",\"protocol\":\"freedom\",\"settings\":{}},{\"tag\":\"block\",\"protocol\":\"blackhole\",\"settings\":{\"response\":{\"type\":\"http\"}}}],\"routing\":{\"domainStrategy\":\"AsIs\",\"rules\":[{\"type\":\"field\",\"inboundTag\":[\"api\"],\"outboundTag\":\"api\",\"enabled\":true},{\"id\":\"5465425548310166497\",\"type\":\"field\",\"outboundTag\":\"direct\",\"domain\":[\"domain:ir\",\"geosite:cn\"],\"enabled\":true},{\"id\":\"5425034033205580637\",\"type\":\"field\",\"outboundTag\":\"direct\",\"ip\":[\"geoip:private\",\"geoip:cn\",\"geoip:ir\"],\"enabled\":true},{\"id\":\"5627785659655799759\",\"type\":\"field\",\"port\":\"0-65535\",\"outboundTag\":\"proxy\",\"enabled\":true}]}}"},{"server_id":"21-1","hostname":"United States","flag":"united_states","hostname_fa":"United States","ip":"lmn1709465405129.lmn15387.info","status":1,"type":"0","Priority":"1","clients":{},"port":443,"redirectTo":"lmn1021.sbs","config":"{\"log\":{\"access\":\"\",\"error\":\"\",\"loglevel\":\"warning\"},\"inbounds\":[{\"tag\":\"socks\",\"port\":10808,\"listen\":\"127.0.0.1\",\"protocol\":\"socks\",\"sniffing\":{\"enabled\":true,\"destOverride\":[\"http\",\"tls\"],\"routeOnly\":false},\"settings\":{\"auth\":\"noauth\",\"udp\":true,\"allowTransparent\":false}},{\"tag\":\"http\",\"port\":10809,\"listen\":\"127.0.0.1\",\"protocol\":\"http\",\"sniffing\":{\"enabled\":true,\"destOverride\":[\"http\",\"tls\"],\"routeOnly\":false},\"settings\":{\"auth\":\"noauth\",\"udp\":true,\"allowTransparent\":false}}],\"outbounds\":[{\"tag\":\"proxy\",\"protocol\":\"vless\",\"settings\":{\"vnext\":[{\"address\":\"104.31.16.66\",\"port\":443,\"users\":[{\"id\":\"376b9861-2fc6-4647-959c-18185cd9c95a\",\"alterId\":0,\"email\":\"t@t.tt\",\"security\":\"auto\",\"encryption\":\"none\",\"flow\":\"\"}]}]},\"streamSettings\":{\"network\":\"ws\",\"security\":\"tls\",\"tlsSettings\":{\"allowInsecure\":true,\"serverName\":\"lmn1709465405129.lmn15387.info\",\"alpn\":[\"h2\",\"http/1.1\"],\"fingerprint\":\"chrome\",\"show\":false},\"wsSettings\":{\"path\":\"/hz2-6ws\",\"headers\":{\"Host\":\"lmn1709465405129.lmn15387.info\"}},\"sockopt\":{\"dialerProxy\":\"fragment\",\"tcpKeepAliveIdle\":100,\"mark\":255}},\"mux\":{\"enabled\":false,\"concurrency\":-1}},{\"tag\":\"fragment\",\"protocol\":\"freedom\",\"settings\":{\"fragment\":{\"packets\":\"tlshello\",\"length\":\"10-20\",\"interval\":\"10-20\"}},\"streamSettings\":{\"sockopt\":{\"TcpNoDelay\":true,\"tcpKeepAliveIdle\":100,\"mark\":255}}},{\"tag\":\"direct\",\"protocol\":\"freedom\",\"settings\":{}},{\"tag\":\"block\",\"protocol\":\"blackhole\",\"settings\":{\"response\":{\"type\":\"http\"}}}],\"routing\":{\"domainStrategy\":\"AsIs\",\"rules\":[{\"type\":\"field\",\"inboundTag\":[\"api\"],\"outboundTag\":\"api\",\"enabled\":true},{\"id\":\"5465425548310166497\",\"type\":\"field\",\"outboundTag\":\"direct\",\"domain\":[\"domain:ir\",\"geosite:cn\"],\"enabled\":true},{\"id\":\"5425034033205580637\",\"type\":\"field\",\"outboundTag\":\"direct\",\"ip\":[\"geoip:private\",\"geoip:cn\",\"geoip:ir\"],\"enabled\":true},{\"id\":\"5627785659655799759\",\"type\":\"field\",\"port\":\"0-65535\",\"outboundTag\":\"proxy\",\"enabled\":true}]}}"},{"server_id":"25-1","hostname":"United States","flag":"united_states","hostname_fa":"United States","ip":"lmn1709465405652.lmn15386.info","status":1,"type":"0","Priority":"1","clients":{},"port":443,"redirectTo":"lmn1025.sbs","config":"{\"log\":{\"access\":\"\",\"error\":\"\",\"loglevel\":\"warning\"},\"inbounds\":[{\"tag\":\"socks\",\"port\":10808,\"listen\":\"127.0.0.1\",\"protocol\":\"socks\",\"sniffing\":{\"enabled\":true,\"destOverride\":[\"http\",\"tls\"],\"routeOnly\":false},\"settings\":{\"auth\":\"noauth\",\"udp\":true,\"allowTransparent\":false}},{\"tag\":\"http\",\"port\":10809,\"listen\":\"127.0.0.1\",\"protocol\":\"http\",\"sniffing\":{\"enabled\":true,\"destOverride\":[\"http\",\"tls\"],\"routeOnly\":false},\"settings\":{\"auth\":\"noauth\",\"udp\":true,\"allowTransparent\":false}}],\"outbounds\":[{\"tag\":\"proxy\",\"protocol\":\"vless\",\"settings\":{\"vnext\":[{\"address\":\"104.31.16.66\",\"port\":443,\"users\":[{\"id\":\"376b9861-2fc6-4647-959c-18185cd9c95a\",\"alterId\":0,\"email\":\"t@t.tt\",\"security\":\"auto\",\"encryption\":\"none\",\"flow\":\"\"}]}]},\"streamSettings\":{\"network\":\"ws\",\"security\":\"tls\",\"tlsSettings\":{\"allowInsecure\":true,\"serverName\":\"lmn1709465405652.lmn15386.info\",\"alpn\":[\"h2\",\"http/1.1\"],\"fingerprint\":\"chrome\",\"show\":false},\"wsSettings\":{\"path\":\"/hz3-5ws\",\"headers\":{\"Host\":\"lmn1709465405652.lmn15386.info\"}},\"sockopt\":{\"dialerProxy\":\"fragment\",\"tcpKeepAliveIdle\":100,\"mark\":255}},\"mux\":{\"enabled\":false,\"concurrency\":-1}},{\"tag\":\"fragment\",\"protocol\":\"freedom\",\"settings\":{\"fragment\":{\"packets\":\"tlshello\",\"length\":\"10-20\",\"interval\":\"10-20\"}},\"streamSettings\":{\"sockopt\":{\"TcpNoDelay\":true,\"tcpKeepAliveIdle\":100,\"mark\":255}}},{\"tag\":\"direct\",\"protocol\":\"freedom\",\"settings\":{}},{\"tag\":\"block\",\"protocol\":\"blackhole\",\"settings\":{\"response\":{\"type\":\"http\"}}}],\"routing\":{\"domainStrategy\":\"AsIs\",\"rules\":[{\"type\":\"field\",\"inboundTag\":[\"api\"],\"outboundTag\":\"api\",\"enabled\":true},{\"id\":\"5465425548310166497\",\"type\":\"field\",\"outboundTag\":\"direct\",\"domain\":[\"domain:ir\",\"geosite:cn\"],\"enabled\":true},{\"id\":\"5425034033205580637\",\"type\":\"field\",\"outboundTag\":\"direct\",\"ip\":[\"geoip:private\",\"geoip:cn\",\"geoip:ir\"],\"enabled\":true},{\"id\":\"5627785659655799759\",\"type\":\"field\",\"port\":\"0-65535\",\"outboundTag\":\"proxy\",\"enabled\":true}]}}"},{"server_id":"5-1","hostname":"Germany","flag":"germany","hostname_fa":"Germany","ip":"lmn1709465405531.lmn15389.info","status":1,"type":"0","Priority":"1","clients":{},"port":443,"redirectTo":"lmn1005.sbs","config":"{\"log\":{\"access\":\"\",\"error\":\"\",\"loglevel\":\"warning\"},\"inbounds\":[{\"tag\":\"socks\",\"port\":10808,\"listen\":\"127.0.0.1\",\"protocol\":\"socks\",\"sniffing\":{\"enabled\":true,\"destOverride\":[\"http\",\"tls\"],\"routeOnly\":false},\"settings\":{\"auth\":\"noauth\",\"udp\":true,\"allowTransparent\":false}},{\"tag\":\"http\",\"port\":10809,\"listen\":\"127.0.0.1\",\"protocol\":\"http\",\"sniffing\":{\"enabled\":true,\"destOverride\":[\"http\",\"tls\"],\"routeOnly\":false},\"settings\":{\"auth\":\"noauth\",\"udp\":true,\"allowTransparent\":false}}],\"outbounds\":[{\"tag\":\"proxy\",\"protocol\":\"vless\",\"settings\":{\"vnext\":[{\"address\":\"104.31.16.66\",\"port\":443,\"users\":[{\"id\":\"376b9861-2fc6-4647-959c-18185cd9c95a\",\"alterId\":0,\"email\":\"t@t.tt\",\"security\":\"auto\",\"encryption\":\"none\",\"flow\":\"\"}]}]},\"streamSettings\":{\"network\":\"ws\",\"security\":\"tls\",\"tlsSettings\":{\"allowInsecure\":true,\"serverName\":\"lmn1709465405531.lmn15389.info\",\"alpn\":[\"h2\",\"http/1.1\"],\"fingerprint\":\"chrome\",\"show\":false},\"wsSettings\":{\"path\":\"/hz2-1ws\",\"headers\":{\"Host\":\"lmn1709465405531.lmn15389.info\"}},\"sockopt\":{\"dialerProxy\":\"fragment\",\"tcpKeepAliveIdle\":100,\"mark\":255}},\"mux\":{\"enabled\":false,\"concurrency\":-1}},{\"tag\":\"fragment\",\"protocol\":\"freedom\",\"settings\":{\"fragment\":{\"packets\":\"tlshello\",\"length\":\"10-20\",\"interval\":\"10-20\"}},\"streamSettings\":{\"sockopt\":{\"TcpNoDelay\":true,\"tcpKeepAliveIdle\":100,\"mark\":255}}},{\"tag\":\"direct\",\"protocol\":\"freedom\",\"settings\":{}},{\"tag\":\"block\",\"protocol\":\"blackhole\",\"settings\":{\"response\":{\"type\":\"http\"}}}],\"routing\":{\"domainStrategy\":\"AsIs\",\"rules\":[{\"type\":\"field\",\"inboundTag\":[\"api\"],\"outboundTag\":\"api\",\"enabled\":true},{\"id\":\"5465425548310166497\",\"type\":\"field\",\"outboundTag\":\"direct\",\"domain\":[\"domain:ir\",\"geosite:cn\"],\"enabled\":true},{\"id\":\"5425034033205580637\",\"type\":\"field\",\"outboundTag\":\"direct\",\"ip\":[\"geoip:private\",\"geoip:cn\",\"geoip:ir\"],\"enabled\":true},{\"id\":\"5627785659655799759\",\"type\":\"field\",\"port\":\"0-65535\",\"outboundTag\":\"proxy\",\"enabled\":true}]}}"},{"server_id":"27-1","hostname":"United States","flag":"united_states","hostname_fa":"United States","ip":"lmn1709465410946.lmn15392.info","status":1,"type":"1","Priority":"1","clients":8156,"port":443,"redirectTo":"lmn1027.sbs","config":"{\"log\":{\"access\":\"\",\"error\":\"\",\"loglevel\":\"warning\"},\"inbounds\":[{\"tag\":\"socks\",\"port\":10808,\"listen\":\"127.0.0.1\",\"protocol\":\"socks\",\"sniffing\":{\"enabled\":true,\"destOverride\":[\"http\",\"tls\"],\"routeOnly\":false},\"settings\":{\"auth\":\"noauth\",\"udp\":true,\"allowTransparent\":false}},{\"tag\":\"http\",\"port\":10809,\"listen\":\"127.0.0.1\",\"protocol\":\"http\",\"sniffing\":{\"enabled\":true,\"destOverride\":[\"http\",\"tls\"],\"routeOnly\":false},\"settings\":{\"auth\":\"noauth\",\"udp\":true,\"allowTransparent\":false}}],\"outbounds\":[{\"tag\":\"proxy\",\"protocol\":\"vless\",\"settings\":{\"vnext\":[{\"address\":\"104.31.16.66\",\"port\":443,\"users\":[{\"id\":\"376b9861-2fc6-4647-959c-18185cd9c95a\",\"alterId\":0,\"email\":\"t@t.tt\",\"security\":\"auto\",\"encryption\":\"none\",\"flow\":\"\"}]}]},\"streamSettings\":{\"network\":\"ws\",\"security\":\"tls\",\"tlsSettings\":{\"allowInsecure\":true,\"serverName\":\"lmn1709465410946.lmn15392.info\",\"alpn\":[\"h2\",\"http/1.1\"],\"fingerprint\":\"chrome\",\"show\":false},\"wsSettings\":{\"path\":\"/hz3-6ws\",\"headers\":{\"Host\":\"lmn1709465410946.lmn15392.info\"}},\"sockopt\":{\"dialerProxy\":\"fragment\",\"tcpKeepAliveIdle\":100,\"mark\":255}},\"mux\":{\"enabled\":false,\"concurrency\":-1}},{\"tag\":\"fragment\",\"protocol\":\"freedom\",\"settings\":{\"fragment\":{\"packets\":\"tlshello\",\"length\":\"10-20\",\"interval\":\"10-20\"}},\"streamSettings\":{\"sockopt\":{\"TcpNoDelay\":true,\"tcpKeepAliveIdle\":100,\"mark\":255}}},{\"tag\":\"direct\",\"protocol\":\"freedom\",\"settings\":{}},{\"tag\":\"block\",\"protocol\":\"blackhole\",\"settings\":{\"response\":{\"type\":\"http\"}}}],\"routing\":{\"domainStrategy\":\"AsIs\",\"rules\":[{\"type\":\"field\",\"inboundTag\":[\"api\"],\"outboundTag\":\"api\",\"enabled\":true},{\"id\":\"5465425548310166497\",\"type\":\"field\",\"outboundTag\":\"direct\",\"domain\":[\"domain:ir\",\"geosite:cn\"],\"enabled\":true},{\"id\":\"5425034033205580637\",\"type\":\"field\",\"outboundTag\":\"direct\",\"ip\":[\"geoip:private\",\"geoip:cn\",\"geoip:ir\"],\"enabled\":true},{\"id\":\"5627785659655799759\",\"type\":\"field\",\"port\":\"0-65535\",\"outboundTag\":\"proxy\",\"enabled\":true}]}}"},{"server_id":"19-1","hostname":"Netherlands","flag":"netherlands","hostname_fa":"Netherlands","ip":"lmn1709465405716.lmn15371.info","status":1,"type":"0","Priority":"1","clients":8156,"port":443,"redirectTo":"lmn1039.sbs","config":"{\"log\":{\"access\":\"\",\"error\":\"\",\"loglevel\":\"warning\"},\"inbounds\":[{\"tag\":\"socks\",\"port\":10808,\"listen\":\"127.0.0.1\",\"protocol\":\"socks\",\"sniffing\":{\"enabled\":true,\"destOverride\":[\"http\",\"tls\"],\"routeOnly\":false},\"settings\":{\"auth\":\"noauth\",\"udp\":true,\"allowTransparent\":false}},{\"tag\":\"http\",\"port\":10809,\"listen\":\"127.0.0.1\",\"protocol\":\"http\",\"sniffing\":{\"enabled\":true,\"destOverride\":[\"http\",\"tls\"],\"routeOnly\":false},\"settings\":{\"auth\":\"noauth\",\"udp\":true,\"allowTransparent\":false}}],\"outbounds\":[{\"tag\":\"proxy\",\"protocol\":\"vless\",\"settings\":{\"vnext\":[{\"address\":\"104.31.16.66\",\"port\":443,\"users\":[{\"id\":\"376b9861-2fc6-4647-959c-18185cd9c95a\",\"alterId\":0,\"email\":\"t@t.tt\",\"security\":\"auto\",\"encryption\":\"none\",\"flow\":\"\"}]}]},\"streamSettings\":{\"network\":\"ws\",\"security\":\"tls\",\"tlsSettings\":{\"allowInsecure\":true,\"serverName\":\"lmn1709465405716.lmn15371.info\",\"alpn\":[\"h2\",\"http/1.1\"],\"fingerprint\":\"chrome\",\"show\":false},\"wsSettings\":{\"path\":\"/hz2-4ws\",\"headers\":{\"Host\":\"lmn1709465405716.lmn15371.info\"}},\"sockopt\":{\"dialerProxy\":\"fragment\",\"tcpKeepAliveIdle\":100,\"mark\":255}},\"mux\":{\"enabled\":false,\"concurrency\":-1}},{\"tag\":\"fragment\",\"protocol\":\"freedom\",\"settings\":{\"fragment\":{\"packets\":\"tlshello\",\"length\":\"10-20\",\"interval\":\"10-20\"}},\"streamSettings\":{\"sockopt\":{\"TcpNoDelay\":true,\"tcpKeepAliveIdle\":100,\"mark\":255}}},{\"tag\":\"direct\",\"protocol\":\"freedom\",\"settings\":{}},{\"tag\":\"block\",\"protocol\":\"blackhole\",\"settings\":{\"response\":{\"type\":\"http\"}}}],\"routing\":{\"domainStrategy\":\"AsIs\",\"rules\":[{\"type\":\"field\",\"inboundTag\":[\"api\"],\"outboundTag\":\"api\",\"enabled\":true},{\"id\":\"5465425548310166497\",\"type\":\"field\",\"outboundTag\":\"direct\",\"domain\":[\"domain:ir\",\"geosite:cn\"],\"enabled\":true},{\"id\":\"5425034033205580637\",\"type\":\"field\",\"outboundTag\":\"direct\",\"ip\":[\"geoip:private\",\"geoip:cn\",\"geoip:ir\"],\"enabled\":true},{\"id\":\"5627785659655799759\",\"type\":\"field\",\"port\":\"0-65535\",\"outboundTag\":\"proxy\",\"enabled\":true}]}}"},{"server_id":"2-1","hostname":"Germany","flag":"germany","hostname_fa":"Germany","ip":"lmn1709465405527.lmn15395.info","status":1,"type":"0","Priority":"1","clients":{},"port":443,"redirectTo":"lmn1030.sbs","config":"{\"log\":{\"access\":\"\",\"error\":\"\",\"loglevel\":\"warning\"},\"inbounds\":[{\"tag\":\"socks\",\"port\":10808,\"listen\":\"127.0.0.1\",\"protocol\":\"socks\",\"sniffing\":{\"enabled\":true,\"destOverride\":[\"http\",\"tls\"],\"routeOnly\":false},\"settings\":{\"auth\":\"noauth\",\"udp\":true,\"allowTransparent\":false}},{\"tag\":\"http\",\"port\":10809,\"listen\":\"127.0.0.1\",\"protocol\":\"http\",\"sniffing\":{\"enabled\":true,\"destOverride\":[\"http\",\"tls\"],\"routeOnly\":false},\"settings\":{\"auth\":\"noauth\",\"udp\":true,\"allowTransparent\":false}}],\"outbounds\":[{\"tag\":\"proxy\",\"protocol\":\"vless\",\"settings\":{\"vnext\":[{\"address\":\"104.31.16.66\",\"port\":443,\"users\":[{\"id\":\"376b9861-2fc6-4647-959c-18185cd9c95a\",\"alterId\":0,\"email\":\"t@t.tt\",\"security\":\"auto\",\"encryption\":\"none\",\"flow\":\"\"}]}]},\"streamSettings\":{\"network\":\"ws\",\"security\":\"tls\",\"tlsSettings\":{\"allowInsecure\":true,\"serverName\":\"lmn1709465405527.lmn15395.info\",\"alpn\":[\"h2\",\"http/1.1\"],\"fingerprint\":\"chrome\",\"show\":false},\"wsSettings\":{\"path\":\"/hz2-6ws\",\"headers\":{\"Host\":\"lmn1709465405527.lmn15395.info\"}},\"sockopt\":{\"dialerProxy\":\"fragment\",\"tcpKeepAliveIdle\":100,\"mark\":255}},\"mux\":{\"enabled\":false,\"concurrency\":-1}},{\"tag\":\"fragment\",\"protocol\":\"freedom\",\"settings\":{\"fragment\":{\"packets\":\"tlshello\",\"length\":\"10-20\",\"interval\":\"10-20\"}},\"streamSettings\":{\"sockopt\":{\"TcpNoDelay\":true,\"tcpKeepAliveIdle\":100,\"mark\":255}}},{\"tag\":\"direct\",\"protocol\":\"freedom\",\"settings\":{}},{\"tag\":\"block\",\"protocol\":\"blackhole\",\"settings\":{\"response\":{\"type\":\"http\"}}}],\"routing\":{\"domainStrategy\":\"AsIs\",\"rules\":[{\"type\":\"field\",\"inboundTag\":[\"api\"],\"outboundTag\":\"api\",\"enabled\":true},{\"id\":\"5465425548310166497\",\"type\":\"field\",\"outboundTag\":\"direct\",\"domain\":[\"domain:ir\",\"geosite:cn\"],\"enabled\":true},{\"id\":\"5425034033205580637\",\"type\":\"field\",\"outboundTag\":\"direct\",\"ip\":[\"geoip:private\",\"geoip:cn\",\"geoip:ir\"],\"enabled\":true},{\"id\":\"5627785659655799759\",\"type\":\"field\",\"port\":\"0-65535\",\"outboundTag\":\"proxy\",\"enabled\":true}]}}"},{"server_id":"16-1","hostname":"United States","flag":"united_states","hostname_fa":"United States","ip":"lmn1709465405135.lmn15381.info","status":1,"type":"0","Priority":"1","clients":{},"port":443,"redirectTo":"lmn1016.sbs","config":"{\"log\":{\"access\":\"\",\"error\":\"\",\"loglevel\":\"warning\"},\"inbounds\":[{\"tag\":\"socks\",\"port\":10808,\"listen\":\"127.0.0.1\",\"protocol\":\"socks\",\"sniffing\":{\"enabled\":true,\"destOverride\":[\"http\",\"tls\"],\"routeOnly\":false},\"settings\":{\"auth\":\"noauth\",\"udp\":true,\"allowTransparent\":false}},{\"tag\":\"http\",\"port\":10809,\"listen\":\"127.0.0.1\",\"protocol\":\"http\",\"sniffing\":{\"enabled\":true,\"destOverride\":[\"http\",\"tls\"],\"routeOnly\":false},\"settings\":{\"auth\":\"noauth\",\"udp\":true,\"allowTransparent\":false}}],\"outbounds\":[{\"tag\":\"proxy\",\"protocol\":\"vless\",\"settings\":{\"vnext\":[{\"address\":\"104.31.16.66\",\"port\":443,\"users\":[{\"id\":\"376b9861-2fc6-4647-959c-18185cd9c95a\",\"alterId\":0,\"email\":\"t@t.tt\",\"security\":\"auto\",\"encryption\":\"none\",\"flow\":\"\"}]}]},\"streamSettings\":{\"network\":\"ws\",\"security\":\"tls\",\"tlsSettings\":{\"allowInsecure\":true,\"serverName\":\"lmn1709465405135.lmn15381.info\",\"alpn\":[\"h2\",\"http/1.1\"],\"fingerprint\":\"chrome\",\"show\":false},\"wsSettings\":{\"path\":\"/hz3-2ws\",\"headers\":{\"Host\":\"lmn1709465405135.lmn15381.info\"}},\"sockopt\":{\"dialerProxy\":\"fragment\",\"tcpKeepAliveIdle\":100,\"mark\":255}},\"mux\":{\"enabled\":false,\"concurrency\":-1}},{\"tag\":\"fragment\",\"protocol\":\"freedom\",\"settings\":{\"fragment\":{\"packets\":\"tlshello\",\"length\":\"10-20\",\"interval\":\"10-20\"}},\"streamSettings\":{\"sockopt\":{\"TcpNoDelay\":true,\"tcpKeepAliveIdle\":100,\"mark\":255}}},{\"tag\":\"direct\",\"protocol\":\"freedom\",\"settings\":{}},{\"tag\":\"block\",\"protocol\":\"blackhole\",\"settings\":{\"response\":{\"type\":\"http\"}}}],\"routing\":{\"domainStrategy\":\"AsIs\",\"rules\":[{\"type\":\"field\",\"inboundTag\":[\"api\"],\"outboundTag\":\"api\",\"enabled\":true},{\"id\":\"5465425548310166497\",\"type\":\"field\",\"outboundTag\":\"direct\",\"domain\":[\"domain:ir\",\"geosite:cn\"],\"enabled\":true},{\"id\":\"5425034033205580637\",\"type\":\"field\",\"outboundTag\":\"direct\",\"ip\":[\"geoip:private\",\"geoip:cn\",\"geoip:ir\"],\"enabled\":true},{\"id\":\"5627785659655799759\",\"type\":\"field\",\"port\":\"0-65535\",\"outboundTag\":\"proxy\",\"enabled\":true}]}}"}],"config":{"_id":"6397464e0aee45297a10d4d8","type":"2","App_Id":"ca-app-pub-2962618104536544~8182319141","acunit":"ca-app-pub-2962618104536544/6569830825","bcunit":"ca-app-pub-2962618104536544/6290419444","native":"ca-app-pub-2962618104536544/6606587320","splash":"ca-app-pub-2962618104536544/6798159010","dcunit":"ca-app-pub-2962618104536544/7919668999","rewarded":"ca-app-pub-2962618104536544/1114825480","versioncode":"579166475","buttontext":"Update","updatetext":"New version available. Update to get new features.","isforceupdate":0,"downloadlink":"http://verify.appsongplay.com/dl/ox-12.apk","gplaylink":"http://play.google.com/store/apps/details?id=com.vpn.oxvpn","shouldverifyconnection":true,"checktraffictimeout":5000,"checktrafficretrycount":2,"splashtimeout":25000,"aftershowtimeout":60000,"appinbackgroundtimeout":60000,"isadvpnserverallowed":true,"isadvpnserverallowedonconnected":true,"shouldverifyadvpnconnection":true,"checkadvpntraffictimeout":5000,"checkadvpntrafficretrycount":2,"advpnserverretrycount":2,"connectionfaliedlogenabled":true,"connectedlogenabled":true,"disconnectedlogenabled":false,"back_urls":"https://ox.appsongplay.com/all,http://newox.appsongplay.com/all,http://162.55.174.50/all,https://github.com/apponboard2019/api/blob/master/ox10.json?raw=true","app":"ox","log_server_url":"http://log.reymarz.xyz/v1/connection","checknetworkurl":"https://pro.ip-api.com/json/?key=a1MgxMeysMPPNV8","verifyadvpnconnectionurl":"http://92.205.161.10/ok.json","verifyconnectionurl":"http://92.205.161.10/ok.json","disconnectinterval":180000000,"isdisconnectcheckerenabled":false,"forcedisconnectenabled":false,"forcedisconnectinterval":200000000},"protocols":[{"_id":"640a8d8541ddda2a4ccffb91","enabled":true,"config":"{\"log\":{\"access\":\"\",\"error\":\"\",\"loglevel\":\"warning\"},\"inbounds\":[{\"tag\":\"socks\",\"port\":10808,\"listen\":\"127.0.0.1\",\"protocol\":\"socks\",\"sniffing\":{\"enabled\":true,\"destOverride\":[\"http\",\"tls\"],\"routeOnly\":false},\"settings\":{\"auth\":\"noauth\",\"udp\":true,\"allowTransparent\":false}},{\"tag\":\"http\",\"port\":10809,\"listen\":\"127.0.0.1\",\"protocol\":\"http\",\"sniffing\":{\"enabled\":true,\"destOverride\":[\"http\",\"tls\"],\"routeOnly\":false},\"settings\":{\"auth\":\"noauth\",\"udp\":true,\"allowTransparent\":false}}],\"outbounds\":[{\"tag\":\"proxy\",\"protocol\":\"vless\",\"settings\":{\"vnext\":[{\"address\":\"@fake_address\",\"port\":443,\"users\":[{\"id\":\"376b9861-2fc6-4647-959c-18185cd9c95a\",\"alterId\":0,\"email\":\"t@t.tt\",\"security\":\"auto\",\"encryption\":\"none\",\"flow\":\"\"}]}]},\"streamSettings\":{\"network\":\"ws\",\"security\":\"tls\",\"tlsSettings\":{\"allowInsecure\":true,\"serverName\":\"@ip\",\"alpn\":[\"h2\",\"http/1.1\"],\"fingerprint\":\"chrome\",\"show\":false},\"wsSettings\":{\"path\":\"/@path\",\"headers\":{\"Host\":\"@ip\"}},\"sockopt\":{\"dialerProxy\":\"fragment\",\"tcpKeepAliveIdle\":100,\"mark\":255}},\"mux\":{\"enabled\":false,\"concurrency\":-1}},{\"tag\":\"fragment\",\"protocol\":\"freedom\",\"settings\":{\"fragment\":{\"packets\":\"tlshello\",\"length\":\"10-20\",\"interval\":\"10-20\"}},\"streamSettings\":{\"sockopt\":{\"TcpNoDelay\":true,\"tcpKeepAliveIdle\":100,\"mark\":255}}},{\"tag\":\"direct\",\"protocol\":\"freedom\",\"settings\":{}},{\"tag\":\"block\",\"protocol\":\"blackhole\",\"settings\":{\"response\":{\"type\":\"http\"}}}],\"routing\":{\"domainStrategy\":\"AsIs\",\"rules\":[{\"type\":\"field\",\"inboundTag\":[\"api\"],\"outboundTag\":\"api\",\"enabled\":true},{\"id\":\"5465425548310166497\",\"type\":\"field\",\"outboundTag\":\"direct\",\"domain\":[\"domain:ir\",\"geosite:cn\"],\"enabled\":true},{\"id\":\"5425034033205580637\",\"type\":\"field\",\"outboundTag\":\"direct\",\"ip\":[\"geoip:private\",\"geoip:cn\",\"geoip:ir\"],\"enabled\":true},{\"id\":\"5627785659655799759\",\"type\":\"field\",\"port\":\"0-65535\",\"outboundTag\":\"proxy\",\"enabled\":true}]}}","name":"general","operator":"general,others"}],"fake_addresses":[{"_id":"647b114dca9ee5237a1f9d69","address":"104.31.16.66","operator":"general","index":"1","addresses":["104.31.16.66"]}]}
